<?xml version='1.0' encoding='UTF-8'?>
<tv generator-info-name="https://github.com/dbghelp">
	<channel id="ntv">
		<display-name>日テレ</display-name>
		<icon src="https://statics.tver.jp/images/icon/ntv.jpg" />
	</channel>
	<channel id="ex">
		<display-name>テレビ朝日</display-name>
		<icon src="https://statics.tver.jp/images/icon/ex.jpg" />
	</channel>
	<channel id="tbs">
		<display-name>TBS</display-name>
		<icon src="https://statics.tver.jp/images/icon/tbs.jpg" />
	</channel>
	<channel id="tx">
		<display-name>テレ東</display-name>
		<icon src="https://statics.tver.jp/images/icon/tx.jpg" />
	</channel>
	<channel id="cx">
		<display-name>フジテレビ</display-name>
		<icon src="https://statics.tver.jp/images/icon/cx.jpg" />
	</channel>
	<programme channel="ntv" start="20260320204500 +0000" stop="20260321100000 +0000">
		<title>配信休止</title>
		<desc> </desc>
		<icon src="https://statics.tver.jp/images/content/thumbnail/live/xlarge/lef5ky5qo0.jpg?v=002f5a62" />
	</programme>
	<programme channel="ntv" start="20260321100000 +0000" stop="20260321125400 +0000">
		<title>1億人の大質問!?笑ってコラえて！</title>
		<desc>北海道から鹿児島県徳之島まで!ダーツ&amp;道の駅伝3時間SP</desc>
		<icon src="https://statics.tver.jp/images/content/thumbnail/live/xlarge/lejbz66wde.jpg?v=e7e63547" />
	</programme>
	<programme channel="ntv" start="20260321125400 +0000" stop="20260321130000 +0000">
		<title>お知らせ</title>
		<desc>リアルタイム配信予定の番組は「日テレ系」タブよりご確認いただけます。</desc>
		<icon src="https://statics.tver.jp/images/content/thumbnail/live/xlarge/le2hdekh7o.jpg?v=25325802" />
	</programme>
	<programme channel="ntv" start="20260321130000 +0000" stop="20260321135400 +0000">
		<title>ヒロミのおせっ買い！</title>
		<desc>【豪華芸能人一世一代の買い物】横山裕が相葉雅紀にサプライズ</desc>
		<icon src="https://statics.tver.jp/images/content/thumbnail/live/xlarge/lewzv328fd.jpg?v=f6127b3e" />
	</programme>
	<programme channel="ntv" start="20260321135400 +0000" stop="20260321201000 +0000">
		<title>配信休止</title>
		<desc> </desc>
		<icon src="https://statics.tver.jp/images/content/thumbnail/live/xlarge/ley0z5lhxt.jpg?v=86949806" />
	</programme>
	<programme channel="ntv" start="20260321201000 +0000" stop="20260322095500 +0000">
		<title>配信休止</title>
		<desc> </desc>
		<icon src="https://statics.tver.jp/images/content/thumbnail/live/xlarge/ledz6b0lp1.jpg?v=69c724bf" />
	</programme>
	<programme channel="ntv" start="20260322095500 +0000" stop="20260322100000 +0000">
		<title>博士は今日も嫉妬する～人生が楽しくなる最新テクノロジー～</title>
		<desc>▽サビを簡単に落とせる技術</desc>
		<icon src="https://statics.tver.jp/images/content/thumbnail/live/xlarge/levsfq3gaj.jpg?v=969d0719" />
	</programme>
	<programme channel="ntv" start="20260322100000 +0000" stop="20260322105800 +0000">
		<title>ザ！鉄腕！DASH!!</title>
		<desc>▽DASH島!夢のアイランドキッチン!?サバニ大改造計画!</desc>
		<icon src="https://statics.tver.jp/images/content/thumbnail/live/xlarge/lef3vs2n8c.jpg?v=d8d1478f" />
	</programme>
	<programme channel="ntv" start="20260322105800 +0000" stop="20260322115400 +0000">
		<title>世界の果てまでイッテQ！</title>
		<desc>名作復活!オウムに出川名言を喋らせよう&amp;みやぞんアクアボード挑戦</desc>
		<icon src="https://statics.tver.jp/images/content/thumbnail/live/xlarge/leno7gz0la.jpg?v=452c9b96" />
	</programme>
	<programme channel="ntv" start="20260322115400 +0000" stop="20260322120000 +0000">
		<title>お知らせ</title>
		<desc>リアルタイム配信予定の番組は「日テレ系」タブよりご確認いただけます。</desc>
		<icon src="https://statics.tver.jp/images/content/thumbnail/live/xlarge/let8vdl9hu.jpg?v=197d903c" />
	</programme>
	<programme channel="ntv" start="20260322120000 +0000" stop="20260322125400 +0000">
		<title>Golden SixTONES</title>
		<desc>▽成田凌&amp;岡山天音が悶絶…道枝めるる出題ラーメン2択Q!!</desc>
		<icon src="https://statics.tver.jp/images/content/thumbnail/live/xlarge/leo5bik021.jpg?v=178bb7ca" />
	</programme>
	<programme channel="ntv" start="20260322125400 +0000" stop="20260322130000 +0000">
		<title>お知らせ</title>
		<desc>リアルタイム配信予定の番組は「日テレ系」タブよりご確認いただけます。</desc>
		<icon src="https://statics.tver.jp/images/content/thumbnail/live/xlarge/len3pf03pt.jpg?v=4d25c67e" />
	</programme>
	<programme channel="ntv" start="20260322130000 +0000" stop="20260322133000 +0000">
		<title>おしゃれクリップ</title>
		<desc>ゲスト 又吉直樹</desc>
		<icon src="https://statics.tver.jp/images/content/thumbnail/live/xlarge/leetp9jxox.jpg?v=66827f50" />
	</programme>
	<programme channel="ntv" start="20260322133000 +0000" stop="20260322142500 +0000">
		<title>パンチドランク・ウーマン −脱獄まであと××日−</title>
		<desc>#9ついに脱獄の時!嘘と罠が交錯…一緒に逃げよう</desc>
		<icon src="https://statics.tver.jp/images/content/thumbnail/live/xlarge/le7kevxrl0.jpg?v=bd047c4e" />
	</programme>
	<programme channel="ntv" start="20260322142500 +0000" stop="20260322193000 +0000">
		<title>配信休止</title>
		<desc> </desc>
		<icon src="https://statics.tver.jp/images/content/thumbnail/live/xlarge/lehyd1cf4z.jpg?v=b9025329" />
	</programme>
	<programme channel="ntv" start="20260322193000 +0000" stop="20260323100000 +0000">
		<title>配信休止</title>
		<desc> </desc>
		<icon src="https://statics.tver.jp/images/content/thumbnail/live/xlarge/legqcy3dvq.jpg?v=3af04fd5" />
	</programme>
	<programme channel="ntv" start="20260323100000 +0000" stop="20260323120000 +0000">
		<title>ヒロミが解決！八王子リホーム</title>
		<desc>▽前代未聞!壊れた土俵が復活!子供達の相撲教室作り</desc>
		<icon src="https://statics.tver.jp/images/content/thumbnail/live/xlarge/letb0dqex0.jpg?v=5cc2138b" />
	</programme>
	<programme channel="ntv" start="20260323120000 +0000" stop="20260323125400 +0000">
		<title>しゃべくり007</title>
		<desc>▽テレビ初登場!!石原伸晃一家&amp;岸田文雄元首相が初しゃべくり!!</desc>
		<icon src="https://statics.tver.jp/images/content/thumbnail/live/xlarge/lebjt0tgr3.jpg?v=1407a883" />
	</programme>
	<programme channel="ntv" start="20260323125400 +0000" stop="20260323130000 +0000">
		<title>お知らせ</title>
		<desc>リアルタイム配信予定の番組は「日テレ系」タブよりご確認いただけます。</desc>
		<icon src="https://statics.tver.jp/images/content/thumbnail/live/xlarge/le9x9l3qg3.jpg?v=a156d035" />
	</programme>
	<programme channel="ntv" start="20260323130000 +0000" stop="20260323140000 +0000">
		<title>月曜から夜ふかし</title>
		<desc>【村上も騒然!未来世界は◯◯になるの!?全国ご当地問題】</desc>
		<icon src="https://statics.tver.jp/images/content/thumbnail/live/xlarge/le4eq50g39.jpg?v=5efb2376" />
	</programme>
	<programme channel="ntv" start="20260323140000 +0000" stop="20260323193000 +0000">
		<title>配信休止</title>
		<desc> </desc>
		<icon src="https://statics.tver.jp/images/content/thumbnail/live/xlarge/leuzs1y7cu.jpg?v=85b8a4b8" />
	</programme>
	<programme channel="ntv" start="20260323193000 +0000" stop="20260324100000 +0000">
		<title>配信休止</title>
		<desc> </desc>
		<icon src="https://statics.tver.jp/images/content/thumbnail/live/xlarge/letr08zow0.jpg?v=d2dc37e8" />
	</programme>
	<programme channel="ntv" start="20260324100000 +0000" stop="20260324105400 +0000">
		<title>オモウマい店</title>
		<desc>【茨城】騒ぐんじゃねぇ中華【神奈川】開けて大興奮!玉手箱チャーハン</desc>
		<icon src="https://statics.tver.jp/images/content/thumbnail/live/xlarge/lefv1izgo0.jpg?v=92a021c1" />
	</programme>
	<programme channel="ntv" start="20260324105400 +0000" stop="20260324110000 +0000">
		<title>お知らせ</title>
		<desc>リアルタイム配信予定の番組は「日テレ系」タブよりご確認いただけます。</desc>
		<icon src="https://statics.tver.jp/images/content/thumbnail/live/xlarge/le993tu4kx.jpg?v=025b8d05" />
	</programme>
	<programme channel="ntv" start="20260324110000 +0000" stop="20260324125400 +0000">
		<title>クイズ！あなたは小学5年生より賢いの？</title>
		<desc>賞金1000万SP【伊沢・羽鳥・かまいたち挑戦!今夜奇跡が!?】</desc>
		<icon src="https://statics.tver.jp/images/content/thumbnail/live/xlarge/lezclk23o4.jpg?v=cf34e1fd" />
	</programme>
	<programme channel="ntv" start="20260324125400 +0000" stop="20260324130000 +0000">
		<title>お知らせ</title>
		<desc>リアルタイム配信予定の番組は「日テレ系」タブよりご確認いただけます。</desc>
		<icon src="https://statics.tver.jp/images/content/thumbnail/live/xlarge/lewchljugt.jpg?v=5d80d0fe" />
	</programme>
	<programme channel="ntv" start="20260324130000 +0000" stop="20260324140000 +0000">
		<title>X秒後の新世界</title>
		<desc>ゲートボール若者が本気出したら全国3位のシニアチームに勝てるか?</desc>
		<icon src="https://statics.tver.jp/images/content/thumbnail/live/xlarge/leid3txur1.jpg?v=2492c231" />
	</programme>
	<programme channel="ntv" start="20260324140000 +0000" stop="20260324193000 +0000">
		<title>配信休止</title>
		<desc> </desc>
		<icon src="https://statics.tver.jp/images/content/thumbnail/live/xlarge/leywbz6myb.jpg?v=8617b01c" />
	</programme>
	<programme channel="ntv" start="20260324193000 +0000" stop="20260325100000 +0000">
		<title>配信休止</title>
		<desc> </desc>
		<icon src="https://statics.tver.jp/images/content/thumbnail/live/xlarge/leg5cxwqe7.jpg?v=d8ea7824" />
	</programme>
	<programme channel="ntv" start="20260325100000 +0000" stop="20260325115400 +0000">
		<title>有吉の壁</title>
		<desc>生放送SP▼史上最大のおもしろ遊園地!豪華ゲストも続々参戦</desc>
		<icon src="https://statics.tver.jp/images/content/thumbnail/live/xlarge/lerz5m4xf1.jpg?v=5967ef70" />
	</programme>
	<programme channel="ntv" start="20260325115400 +0000" stop="20260325120000 +0000">
		<title>お知らせ</title>
		<desc>リアルタイム配信予定の番組は「日テレ系」タブよりご確認いただけます。</desc>
		<icon src="https://statics.tver.jp/images/content/thumbnail/live/xlarge/lem5kvsidk.jpg?v=90fb26e2" />
	</programme>
	<programme channel="ntv" start="20260325120000 +0000" stop="20260325125400 +0000">
		<title>上田と女が吠える夜</title>
		<desc>▽東京・名古屋・大阪の女が大激論!!最も魅力的な都市はどこ?</desc>
		<icon src="https://statics.tver.jp/images/content/thumbnail/live/xlarge/lep4vfnpbf.jpg?v=0bd63844" />
	</programme>
	<programme channel="ntv" start="20260325125400 +0000" stop="20260325130000 +0000">
		<title>お知らせ</title>
		<desc>リアルタイム配信予定の番組は「日テレ系」タブよりご確認いただけます。</desc>
		<icon src="https://statics.tver.jp/images/content/thumbnail/live/xlarge/le7bckq0cq.jpg?v=eb4eccf1" />
	</programme>
	<programme channel="ntv" start="20260325130000 +0000" stop="20260325140000 +0000">
		<title>冬のなんかさ、春のなんかね</title>
		<desc>最終話 『冬の晴れた日』二人が辿り着いた結末は…</desc>
		<icon src="https://statics.tver.jp/images/content/thumbnail/live/xlarge/lenaait5kt.jpg?v=85fe3626" />
	</programme>
	<programme channel="ntv" start="20260325140000 +0000" stop="20260325193000 +0000">
		<title>配信休止</title>
		<desc> </desc>
		<icon src="https://statics.tver.jp/images/content/thumbnail/live/xlarge/lebzlfsn7m.jpg?v=7c0b08d0" />
	</programme>
	<programme channel="ntv" start="20260325193000 +0000" stop="20260326100000 +0000">
		<title>配信休止</title>
		<desc> </desc>
		<icon src="https://statics.tver.jp/images/content/thumbnail/live/xlarge/le2icyt1vr.jpg?v=47f39c19" />
	</programme>
	<programme channel="ntv" start="20260326100000 +0000" stop="20260326125400 +0000">
		<title>秘密のケンミンSHOW極</title>
		<desc>怒涛の3時間!大九州祭り&amp;上京しても心は県民SP</desc>
		<icon src="https://statics.tver.jp/images/content/thumbnail/live/xlarge/lef45e37sz.jpg?v=385a07f6" />
	</programme>
	<programme channel="ntv" start="20260326125400 +0000" stop="20260326130000 +0000">
		<title>お知らせ</title>
		<desc>リアルタイム配信予定の番組は「日テレ系」タブよりご確認いただけます。</desc>
		<icon src="https://statics.tver.jp/images/content/thumbnail/live/xlarge/lepp7o634p.jpg?v=94601782" />
	</programme>
	<programme channel="ntv" start="20260326130000 +0000" stop="20260326140000 +0000">
		<title>見取り図の間取り図ミステリー</title>
		<desc>謎の激安スペシャル</desc>
		<icon src="https://statics.tver.jp/images/content/thumbnail/live/xlarge/lelabeqhuw.jpg?v=43677fb7" />
	</programme>
	<programme channel="ntv" start="20260326140000 +0000" stop="20260326193000 +0000">
		<title>配信休止</title>
		<desc> </desc>
		<icon src="https://statics.tver.jp/images/content/thumbnail/live/xlarge/lek2e5y6nz.jpg?v=189ca537" />
	</programme>
	<programme channel="ntv" start="20260326193000 +0000" stop="20260327204500 +0000">
		<title>配信休止</title>
		<desc> </desc>
		<icon src="https://statics.tver.jp/images/content/thumbnail/live/xlarge/le75y54kdo.jpg?v=53c1359f" />
	</programme>
	<programme channel="ntv" start="20260327204500 +0000" stop="20260328100000 +0000">
		<title>配信休止</title>
		<desc> </desc>
		<icon src="https://statics.tver.jp/images/content/thumbnail/live/xlarge/lessag5xp7.jpg?v=f4d6ece7" />
	</programme>
	<programme channel="ntv" start="20260328100000 +0000" stop="20260328125400 +0000">
		<title>THE FLOOR</title>
		<desc>▽即答したくなる世界的陣取りゲームで賞金1千万▽MC岡田准一</desc>
		<icon src="https://statics.tver.jp/images/content/thumbnail/live/xlarge/led4wqlldi.jpg?v=2a854b43" />
	</programme>
	<programme channel="ntv" start="20260328125400 +0000" stop="20260328130000 +0000">
		<title>お知らせ</title>
		<desc>リアルタイム配信予定の番組は「日テレ系」タブよりご確認いただけます。</desc>
		<icon src="https://statics.tver.jp/images/content/thumbnail/live/xlarge/lepfykszqg.jpg?v=7e2f0fb6" />
	</programme>
	<programme channel="ntv" start="20260328130000 +0000" stop="20260328135400 +0000">
		<title>メシドラ　～兼近＆真之介のグルメドライブ～</title>
		<desc>SP赤西仁登場!最新バスケマシンで白熱バトル&amp;ダイアン津田に緊急電話!?</desc>
		<icon src="https://statics.tver.jp/images/content/thumbnail/live/xlarge/lefil4gkl0.jpg?v=c0801af0" />
	</programme>
	<programme channel="ntv" start="20260328135400 +0000" stop="20260328202500 +0000">
		<title>配信休止</title>
		<desc> </desc>
		<icon src="https://statics.tver.jp/images/content/thumbnail/live/xlarge/leka3api09.jpg?v=28b5c05d" />
	</programme>
	<programme channel="ntv" start="20260328202500 +0000" stop="20260329095500 +0000">
		<title>配信休止</title>
		<desc> </desc>
		<icon src="https://statics.tver.jp/images/content/thumbnail/live/xlarge/leyjlhw7zf.jpg?v=c0587bb9" />
	</programme>
	<programme channel="ntv" start="20260329095500 +0000" stop="20260329100000 +0000">
		<title>博士は今日も嫉妬する～人生が楽しくなる最新テクノロジー～</title>
		<desc>博士が思わず嫉妬する明日が楽しくなる最新テクノロジーをご紹介!!</desc>
		<icon src="https://statics.tver.jp/images/content/thumbnail/live/xlarge/le6si8r31u.jpg?v=4ab6ac9c" />
	</programme>
	<programme channel="ntv" start="20260329100000 +0000" stop="20260329115400 +0000">
		<title>世界の果てまでイッテQ！</title>
		<desc>2時間SP!温泉同好会に新弟子・川口春奈が参戦&amp;新企画!世界遺産駅伝</desc>
		<icon src="https://statics.tver.jp/images/content/thumbnail/live/xlarge/le2r0udewh.jpg?v=17e7d85b" />
	</programme>
	<programme channel="ntv" start="20260329115400 +0000" stop="20260329120000 +0000">
		<title>お知らせ</title>
		<desc>リアルタイム配信予定の番組は「日テレ系」タブよりご確認いただけます。</desc>
		<icon src="https://statics.tver.jp/images/content/thumbnail/live/xlarge/lejebziaeu.jpg?v=8d6ac80d" />
	</programme>
	<programme channel="ntv" start="20260329120000 +0000" stop="20260329125400 +0000">
		<title>Golden SixTONES</title>
		<desc>▽「国宝」森七菜&amp;チョコプラが初タッグ!!新脳トレクイズSP</desc>
		<icon src="https://statics.tver.jp/images/content/thumbnail/live/xlarge/le1h4gdu9k.jpg?v=b7735647" />
	</programme>
	<programme channel="ntv" start="20260329125400 +0000" stop="20260329130000 +0000">
		<title>お知らせ</title>
		<desc>リアルタイム配信予定の番組は「日テレ系」タブよりご確認いただけます。</desc>
		<icon src="https://statics.tver.jp/images/content/thumbnail/live/xlarge/lepk7uxe4k.jpg?v=ba631f5b" />
	</programme>
	<programme channel="ntv" start="20260329130000 +0000" stop="20260329140000 +0000">
		<title>おしゃれクリップ</title>
		<desc>ゲスト 和田アキ子</desc>
		<icon src="https://statics.tver.jp/images/content/thumbnail/live/xlarge/leefu2x4h8.jpg?v=a79593f7" />
	</programme>
	<programme channel="ntv" start="20260329140000 +0000" stop="20260329145500 +0000">
		<title>パンチドランク・ウーマン −脱獄まであと××日−</title>
		<desc>#10(最終話)禁断の脱獄!2人が手にするのは愛か?絶望か?</desc>
		<icon src="https://statics.tver.jp/images/content/thumbnail/live/xlarge/lecc27swrv.jpg?v=2fcc2dd4" />
	</programme>
	<programme channel="ntv" start="20260329145500 +0000" stop="20260329193000 +0000">
		<title>配信休止</title>
		<desc> </desc>
		<icon src="https://statics.tver.jp/images/content/thumbnail/live/xlarge/le5bbb7fin.jpg?v=3745eca9" />
	</programme>
	<programme channel="ntv" start="20260329193000 +0000" stop="20260330100000 +0000">
		<title>配信休止</title>
		<desc> </desc>
		<icon src="https://statics.tver.jp/images/content/thumbnail/live/xlarge/lesdu5vu9c.jpg?v=7567ba4b" />
	</programme>
	<programme channel="ntv" start="20260330100000 +0000" stop="20260330125400 +0000">
		<title>世界まる見え！テレビ特捜部</title>
		<desc>ミステリークイズSPさんま襲来!永瀬廉・吉川愛ら豪華ゲスト謎解き</desc>
		<icon src="https://statics.tver.jp/images/content/thumbnail/live/xlarge/leynbaoo9h.jpg?v=b6de1314" />
	</programme>
	<programme channel="ntv" start="20260330125400 +0000" stop="20260330130000 +0000">
		<title>お知らせ</title>
		<desc>リアルタイム配信予定の番組は「日テレ系」タブよりご確認いただけます。</desc>
		<icon src="https://statics.tver.jp/images/content/thumbnail/live/xlarge/lei3h1ei0y.jpg?v=c82d06e1" />
	</programme>
	<programme channel="ntv" start="20260330130000 +0000" stop="20260330140000 +0000">
		<title>月曜から夜ふかし</title>
		<desc>【春恒例!上京する人へのアドバイスを聞いてみた件】</desc>
		<icon src="https://statics.tver.jp/images/content/thumbnail/live/xlarge/le4qi4roie.jpg?v=d1054fce" />
	</programme>
	<programme channel="ntv" start="20260330140000 +0000" stop="20260330193000 +0000">
		<title>配信休止</title>
		<desc> </desc>
		<icon src="https://statics.tver.jp/images/content/thumbnail/live/xlarge/lexl90gcnm.jpg?v=db7247d5" />
	</programme>
	<programme channel="ntv" start="20260330193000 +0000" stop="20260331100000 +0000">
		<title>配信休止</title>
		<desc> </desc>
		<icon src="https://statics.tver.jp/images/content/thumbnail/live/xlarge/lefalto6lp.jpg?v=028b2e9b" />
	</programme>
	<programme channel="ntv" start="20260331100000 +0000" stop="20260331115400 +0000">
		<title>オモウマい店</title>
		<desc>2時間SP</desc>
		<icon src="https://statics.tver.jp/images/content/thumbnail/live/xlarge/le4a2383p4.jpg?v=45b81615" />
	</programme>
	<programme channel="ntv" start="20260331115400 +0000" stop="20260331120000 +0000">
		<title>お知らせ</title>
		<desc>リアルタイム配信予定の番組は「日テレ系」タブよりご確認いただけます。</desc>
		<icon src="https://statics.tver.jp/images/content/thumbnail/live/xlarge/lemb7x4waw.jpg?v=0d23ec32" />
	</programme>
	<programme channel="ntv" start="20260331120000 +0000" stop="20260331135400 +0000">
		<title>X秒後の新世界</title>
		<desc>春の2時間スペシャル</desc>
		<icon src="https://statics.tver.jp/images/content/thumbnail/live/xlarge/leou8i0vdi.jpg?v=7509a29e" />
	</programme>
	<programme channel="ntv" start="20260331135400 +0000" stop="20260331193000 +0000">
		<title>配信休止</title>
		<desc> </desc>
		<icon src="https://statics.tver.jp/images/content/thumbnail/live/xlarge/lez67ulw1g.jpg?v=459bac3a" />
	</programme>
	<programme channel="ntv" start="20260331193000 +0000" stop="20260401100000 +0000">
		<title>配信休止</title>
		<desc> </desc>
		<icon src="https://statics.tver.jp/images/content/thumbnail/live/xlarge/letjq9z6gw.jpg?v=d9ff6fc9" />
	</programme>
	<programme channel="ntv" start="20260401100000 +0000" stop="20260401120000 +0000">
		<title>千鳥かまいたちゴールデンアワー</title>
		<desc>2時間SP</desc>
		<icon src="https://statics.tver.jp/images/content/thumbnail/live/xlarge/ledwtpvoc0.jpg?v=f7c6388c" />
	</programme>
	<programme channel="ntv" start="20260401120000 +0000" stop="20260401135400 +0000">
		<title>上田と女が吠える夜</title>
		<desc>SP</desc>
		<icon src="https://statics.tver.jp/images/content/thumbnail/live/xlarge/le25gomye5.jpg?v=5795e46d" />
	</programme>
	<programme channel="ntv" start="20260401135400 +0000" stop="20260401193000 +0000">
		<title>配信休止</title>
		<desc> </desc>
		<icon src="https://statics.tver.jp/images/content/thumbnail/live/xlarge/lexuep39gr.jpg?v=62aa5b30" />
	</programme>
	<programme channel="ntv" start="20260401193000 +0000" stop="20260402100000 +0000">
		<title>配信休止</title>
		<desc> </desc>
		<icon src="https://statics.tver.jp/images/content/thumbnail/live/xlarge/lenep48oya.jpg?v=6956f0e5" />
	</programme>
	<programme channel="ntv" start="20260402100000 +0000" stop="20260402105400 +0000">
		<title>THE突破ファイル</title>
		<desc>Gメン&amp;草薙バイト 春の新ドラマコラボSP</desc>
		<icon src="https://statics.tver.jp/images/content/thumbnail/live/xlarge/lezdjkfk87.jpg?v=b0d318ea" />
	</programme>
	<programme channel="ntv" start="20260402105400 +0000" stop="20260402115400 +0000">
		<title>ぐるぐるナインティナイン</title>
		<desc>町田啓太ゴチ初登場!!増田がバラエティー指導&amp;佐野が人気おもちゃで対決</desc>
		<icon src="https://statics.tver.jp/images/content/thumbnail/live/xlarge/leehb3kaqa.jpg?v=118661e7" />
	</programme>
	<programme channel="ntv" start="20260402115400 +0000" stop="20260402125400 +0000">
		<title>秘密のケンミンSHOW極</title>
		<desc>愛知味噌煮込みうどん&amp;群馬上毛かるたの危機!?</desc>
		<icon src="https://statics.tver.jp/images/content/thumbnail/live/xlarge/leo6p94bb3.jpg?v=619156a3" />
	</programme>
	<programme channel="ntv" start="20260402125400 +0000" stop="20260402130000 +0000">
		<title>お知らせ</title>
		<desc>リアルタイム配信予定の番組は「日テレ系」タブよりご確認いただけます。</desc>
		<icon src="https://statics.tver.jp/images/content/thumbnail/live/xlarge/lejwk21g86.jpg?v=edf17773" />
	</programme>
	<programme channel="ntv" start="20260402130000 +0000" stop="20260402135400 +0000">
		<title>見取り図の間取り図ミステリー</title>
		<desc>4月2日 よる１０時００分～リアルタイム配信！</desc>
		<icon src="https://statics.tver.jp/images/content/thumbnail/live/xlarge/lec1u0pif5.jpg?v=4b324d05" />
	</programme>
	<programme channel="ntv" start="20260402135400 +0000" stop="20260402193000 +0000">
		<title>配信休止</title>
		<desc> </desc>
		<icon src="https://statics.tver.jp/images/content/thumbnail/live/xlarge/legb8p4lko.jpg?v=bd364cb0" />
	</programme>
	<programme channel="ntv" start="20260402193000 +0000" stop="20260403100000 +0000">
		<title>配信休止</title>
		<desc> </desc>
		<icon src="https://statics.tver.jp/images/content/thumbnail/live/xlarge/le0g5j8339.jpg?v=8e1c66b8" />
	</programme>
	<programme channel="ntv" start="20260403100000 +0000" stop="20260403115400 +0000">
		<title>日テレ系クイズフェスティバル2026春</title>
		<desc>日テレ系新番組が集う祭典が開幕！！</desc>
		<icon src="https://statics.tver.jp/images/content/thumbnail/live/xlarge/leair85nj0.jpg?v=be5e9152" />
	</programme>
	<programme channel="ex" start="20260320111000 +0000" stop="20260320125400 +0000">
		<title>徹子の部屋</title>
		<desc>特別編 フィギュア界の歴史を変えたりくりゅうペア 今夜明かされる金メダルの秘密</desc>
		<icon src="https://statics.tver.jp/images/content/thumbnail/live/xlarge/lew1w1euyn.jpg?v=048a0c23" />
	</programme>
	<programme channel="ex" start="20260320125400 +0000" stop="20260320141000 +0000">
		<title>報道ステーション</title>
		<desc>ホルムズ海峡をめぐり攻防…アメリカの要求と日本の回答…注目の首脳会談を詳報▽ＢＴＳ“復活”前夜…ソウルが厳戒態勢に▽連休は警報級の暴風も▽ＭＬＢほか</desc>
		<icon src="https://statics.tver.jp/images/content/thumbnail/live/xlarge/legzmc5hsm.jpg?v=a2289a26" />
	</programme>
	<programme channel="ex" start="20260320141000 +0000" stop="20260321093000 +0000">
		<title>No programme</title>
		<desc>No programme</desc>
		<icon src="https://statics.tver.jp/images/icon/ex.jpg" />
	</programme>
	<programme channel="ex" start="20260321093000 +0000" stop="20260321120000 +0000">
		<title>サンドウィッチマン＆芦田愛菜の博士ちゃん</title>
		<desc>"美しき要塞都市" 世界遺産 ドゥブロヴニクＳＰ</desc>
		<icon src="https://statics.tver.jp/images/content/thumbnail/live/xlarge/le8fyvihs3.jpg?v=1f6d2acb" />
	</programme>
	<programme channel="ex" start="20260321120000 +0000" stop="20260321135400 +0000">
		<title>森英恵 Butterfly beyond　テレビ朝日ドラマプレミアム</title>
		<desc>生誕１００年！世界を魅了したファッションデザイナー森英恵。戦後、新宿に店を構え道なき道を切り拓いていくが…？蝶のモチーフ誕生秘話!?知られざる若き日の奮闘を描く!!</desc>
		<icon src="https://statics.tver.jp/images/content/thumbnail/live/xlarge/let96zaxbs.jpg?v=c01cd749" />
	</programme>
	<programme channel="ex" start="20260321135400 +0000" stop="20260321140000 +0000">
		<title>No programme</title>
		<desc>No programme</desc>
		<icon src="https://statics.tver.jp/images/icon/ex.jpg" />
	</programme>
	<programme channel="ex" start="20260321140000 +0000" stop="20260321143000 +0000">
		<title>サタデーステーション</title>
		<desc>高島彩▽速報！BTSカムバック公演…ソウル超厳戒態勢▽３連休お花見にも物価高直撃…サクラの老木化問題と対策は?▽イラン最新情勢▽大相撲春場所…優勝の行方は▽大谷翔平</desc>
		<icon src="https://statics.tver.jp/images/content/thumbnail/live/xlarge/lev4ey8gwy.jpg?v=97bfe65c" />
	</programme>
	<programme channel="ex" start="20260321143000 +0000" stop="20260322095600 +0000">
		<title>No programme</title>
		<desc>No programme</desc>
		<icon src="https://statics.tver.jp/images/icon/ex.jpg" />
	</programme>
	<programme channel="ex" start="20260322095600 +0000" stop="20260322105000 +0000">
		<title>ナニコレ珍百景</title>
		<desc>群馬vs栃木vs茨城　意地とプライドをかけた北関東Ｎｏ．１決定戦ＳＰ！！</desc>
		<icon src="https://statics.tver.jp/images/content/thumbnail/live/xlarge/led677ilyj.jpg?v=3f04466c" />
	</programme>
	<programme channel="ex" start="20260322105000 +0000" stop="20260322105400 +0000">
		<title>No programme</title>
		<desc>No programme</desc>
		<icon src="https://statics.tver.jp/images/icon/ex.jpg" />
	</programme>
	<programme channel="ex" start="20260322105400 +0000" stop="20260322115600 +0000">
		<title>ポツンと一軒家</title>
		<desc>衛星写真で発見！“何でこんな所に？”という場所に、ポツンと建つ一軒家を日本全国大捜索！</desc>
		<icon src="https://statics.tver.jp/images/content/thumbnail/live/xlarge/ledr19uq0h.jpg?v=14817de9" />
	</programme>
	<programme channel="ex" start="20260322115600 +0000" stop="20260322131500 +0000">
		<title>有働Times</title>
		<desc>「イラン国内の発電所を破壊する」トランプ氏“４８時間以内にホルムズ海峡開放”要求▽イラン軍もインフラ攻撃表明…日本船の海峡通過は▽ＢＴＳ復活ライブ！ファン密着</desc>
		<icon src="https://statics.tver.jp/images/content/thumbnail/live/xlarge/lewj805lnm.jpg?v=b5e364ec" />
	</programme>
	<programme channel="ex" start="20260322131500 +0000" stop="20260322140900 +0000">
		<title>朝メシまで。</title>
		<desc>長さ６４メートル！真夜中にプロが挑む 《巨大風車の運搬に密着SP》</desc>
		<icon src="https://statics.tver.jp/images/content/thumbnail/live/xlarge/learr14ad7.jpg?v=73bdd494" />
	</programme>
	<programme channel="ex" start="20260322140900 +0000" stop="20260323100000 +0000">
		<title>No programme</title>
		<desc>No programme</desc>
		<icon src="https://statics.tver.jp/images/icon/ex.jpg" />
	</programme>
	<programme channel="ex" start="20260323100000 +0000" stop="20260323125400 +0000">
		<title>帰れマンデー見っけ隊!!</title>
		<desc>日本中を旅して、色んなものを見つける旅！さらに、その課題となるものを見つけるまでは帰れない！タカアンドトシとサンドウィッチマンがゲストとともに旅します！</desc>
		<icon src="https://statics.tver.jp/images/content/thumbnail/live/xlarge/lem4h5g327.jpg?v=62792c28" />
	</programme>
	<programme channel="ex" start="20260323125400 +0000" stop="20260323141000 +0000">
		<title>報道ステーション</title>
		<desc>ホルムズ海峡封鎖から３週間、燃料不足懸念…業界団体から“悲鳴”▽前線停滞で雨続きに▽春場所…一夜明け会見▽今週開幕ＭＬＢ！大谷翔平▽センバツ</desc>
		<icon src="https://statics.tver.jp/images/content/thumbnail/live/xlarge/lemzavur54.jpg?v=90d3a4b8" />
	</programme>
	<programme channel="ex" start="20260323141000 +0000" stop="20260324100000 +0000">
		<title>No programme</title>
		<desc>No programme</desc>
		<icon src="https://statics.tver.jp/images/icon/ex.jpg" />
	</programme>
	<programme channel="ex" start="20260324100000 +0000" stop="20260324125400 +0000">
		<title>日本探求アカデミックバラエティ　火曜の良純孝太郎</title>
		<desc>良純＆孝太郎が東京・渋谷を大冒険SP！ ボートに乗り込み渋谷川の源流を辿る！</desc>
		<icon src="https://statics.tver.jp/images/content/thumbnail/live/xlarge/lewz81axlf.jpg?v=63f37a17" />
	</programme>
	<programme channel="ex" start="20260324125400 +0000" stop="20260324141000 +0000">
		<title>報道ステーション</title>
		<desc>期限を「５日間延長」アメリカ・トランプ氏とイラン…“和平協議”進展は▽石油国家備蓄放出へ▽各地４月並み暖かさ▽今永昇太・佐々木朗希がオープン戦、最終登板ほか</desc>
		<icon src="https://statics.tver.jp/images/content/thumbnail/live/xlarge/le39f7bq7x.jpg?v=ce1e6eb1" />
	</programme>
	<programme channel="ex" start="20260324141000 +0000" stop="20260325125400 +0000">
		<title>No programme</title>
		<desc>No programme</desc>
		<icon src="https://statics.tver.jp/images/icon/ex.jpg" />
	</programme>
	<programme channel="ex" start="20260325125400 +0000" stop="20260325141000 +0000">
		<title>報道ステーション</title>
		<desc>アメリカ・イラン協議の実現は…緊張緩和へ駆け引きも▽高市総理が訪米報告…首脳会談をめぐり国会論戦▽太平洋側は強い雨に▽大谷翔平オープン戦…最終登板▽センバツ</desc>
		<icon src="https://statics.tver.jp/images/content/thumbnail/live/xlarge/leces2q13p.jpg?v=17d24801" />
	</programme>
	<programme channel="ex" start="20260325141000 +0000" stop="20260326100000 +0000">
		<title>No programme</title>
		<desc>No programme</desc>
		<icon src="https://statics.tver.jp/images/icon/ex.jpg" />
	</programme>
	<programme channel="ex" start="20260326100000 +0000" stop="20260326125400 +0000">
		<title>相葉ヒロミのお困りですカー？</title>
		<desc>【拡大！春の３時間SP】こっそりプロポーズ大作戦＆池の水抜いて生き物救出</desc>
		<icon src="https://statics.tver.jp/images/content/thumbnail/live/xlarge/leuazmwqzz.jpg?v=c405237f" />
	</programme>
	<programme channel="ex" start="20260326125400 +0000" stop="20260326141000 +0000">
		<title>報道ステーション</title>
		<desc>戦闘から１カ月目前で実現間近？それとも…アメリカ・イラン協議の行方は▽石油の国家備蓄を放出▽広範囲で強雨＆強風▽大谷翔平＆山本由伸…開幕前日▽坂本花織</desc>
		<icon src="https://statics.tver.jp/images/content/thumbnail/live/xlarge/lemko8ci0t.jpg?v=a0c4780e" />
	</programme>
	<programme channel="ex" start="20260326141000 +0000" stop="20260327095000 +0000">
		<title>No programme</title>
		<desc>No programme</desc>
		<icon src="https://statics.tver.jp/images/icon/ex.jpg" />
	</programme>
	<programme channel="ex" start="20260327095000 +0000" stop="20260327110000 +0000">
		<title>ザワつく！ 金曜日</title>
		<desc>一茂さん マネージャーと衝突！？＆ 全国から厳選！絶品いちご＆いちごスイーツ</desc>
		<icon src="https://statics.tver.jp/images/content/thumbnail/live/xlarge/lemmm28q7e.jpg?v=ac54d6a9" />
	</programme>
	<programme channel="ex" start="20260327110000 +0000" stop="20260327125400 +0000">
		<title>No programme</title>
		<desc>No programme</desc>
		<icon src="https://statics.tver.jp/images/icon/ex.jpg" />
	</programme>
	<programme channel="ex" start="20260327125400 +0000" stop="20260327141000 +0000">
		<title>報道ステーション</title>
		<desc>イラン協議拒否にアメリカは…“地上戦”の懸念も▽最高裁で逆転判決？クマ駆除免許取り消し▽週末、桜見頃も傘出番▽大谷翔平＆山本由伸先発…松坂大輔が取材</desc>
		<icon src="https://statics.tver.jp/images/content/thumbnail/live/xlarge/leh8is16gq.jpg?v=04c70f48" />
	</programme>
	<programme channel="ex" start="20260327141000 +0000" stop="20260328093000 +0000">
		<title>No programme</title>
		<desc>No programme</desc>
		<icon src="https://statics.tver.jp/images/icon/ex.jpg" />
	</programme>
	<programme channel="ex" start="20260328093000 +0000" stop="20260328130000 +0000">
		<title>芸能人格付けチェックBASIC　春の３時間半スペシャル</title>
		<desc>「ロックバンド」チェックにHOUND DOGが 登場！「映画監督」チェックには、映画ド素人の M−1王者「たくろう」が参戦！</desc>
		<icon src="https://statics.tver.jp/images/content/thumbnail/live/xlarge/lefpm74mnr.jpg?v=2ec6c8a3" />
	</programme>
	<programme channel="ex" start="20260328130000 +0000" stop="20260328135200 +0000">
		<title>サタデーステーション</title>
		<desc>「ニュースを丁寧に、そして鋭く」。高島彩が土曜夜に最新ニュースをＬＩＶＥでお届け！スタジオで徹底解説＆１週間の話題を「独自取材」で！</desc>
		<icon src="https://statics.tver.jp/images/content/thumbnail/live/xlarge/lefbiokhpd.jpg?v=b2f2d5ab" />
	</programme>
	<programme channel="ex" start="20260329095600 +0000" stop="20260329115600 +0000">
		<title>ポツンと一軒家</title>
		<desc>春の２時間ＳＰ！大分県の深い山奥で、趣味が生きがいのご主人と、長女夫妻の暮らしぶりに密着！夢を楽しく実現していく家族２世帯のケセラセラな生活とは…！</desc>
		<icon src="https://statics.tver.jp/images/content/thumbnail/live/xlarge/leuf2x2q9i.jpg?v=ed4545b8" />
	</programme>
	<programme channel="ex" start="20260329115600 +0000" stop="20260329131500 +0000">
		<title>有働Times</title>
		<desc>日曜夜、有働由美子が視聴者をおもてなし！ニュースのナゼを独自視点で徹底深掘り▽千々岩官邸キャップ解説▽週末スポーツを超速報！▽片岡信和“ピアノ弾き語り天気”</desc>
		<icon src="https://statics.tver.jp/images/content/thumbnail/live/xlarge/lerggqlzxs.jpg?v=85324be4" />
	</programme>
	<programme channel="ex" start="20260330100000 +0000" stop="20260330113000 +0000">
		<title>帰れマンデー見っけ隊!!</title>
		<desc>春のグルメ祭り！栃木の人気ローカルチェーン店で帰れま１０特別編</desc>
		<icon src="https://statics.tver.jp/images/content/thumbnail/live/xlarge/le116b73sh.jpg?v=a93cc83b" />
	</programme>
	<programme channel="ex" start="20260330125400 +0000" stop="20260330141000 +0000">
		<title>報道ステーション</title>
		<desc>「深く、力強く、きょう色々。」大越健介キャスターが、きょう知りたいニュースを“深い洞察”と“平たい言葉”でお送りします。</desc>
		<icon src="https://statics.tver.jp/images/content/thumbnail/live/xlarge/le2gb48bl2.jpg?v=df4ac244" />
	</programme>
	<programme channel="ex" start="20260331100000 +0000" stop="20260331111000 +0000">
		<title>孝太郎＆ちさ子　プラチナファミリー 華麗なる一家をのぞき見</title>
		<desc>日本人誰もが知る有名ＣＭでもおなじみの“あの木”がある公園の所有者＆皇族とも交流のあるハワイ島コナのプラチナさん！ちさ子＆孝太郎も衝撃の大豪邸に潜入！</desc>
		<icon src="https://statics.tver.jp/images/content/thumbnail/live/xlarge/le5e6ieod4.jpg?v=5401a294" />
	</programme>
	<programme channel="ex" start="20260331111000 +0000" stop="20260331125400 +0000">
		<title>謎解き！伝説のミステリー</title>
		<desc>※詳細が決まり次第、お知らせいたします</desc>
		<icon src="https://statics.tver.jp/images/content/thumbnail/live/xlarge/leb0pgy39f.jpg?v=aca9b676" />
	</programme>
	<programme channel="ex" start="20260331125400 +0000" stop="20260331141000 +0000">
		<title>報道ステーション</title>
		<desc>「深く、力強く、きょう色々。」大越健介キャスターが、きょう知りたいニュースを“深い洞察”と“平たい言葉”でお送りします。</desc>
		<icon src="https://statics.tver.jp/images/content/thumbnail/live/xlarge/letcukea4l.jpg?v=23621d05" />
	</programme>
	<programme channel="ex" start="20260401100000 +0000" stop="20260401125400 +0000">
		<title>朝メシまで。</title>
		<desc>私達が寝ている夜に仕事をスタートして朝まで働く…そんな方々が“１日のシメに食べる朝ご飯”とは!?知られざる深夜のお仕事を朝メシまで密着するドキュメントバラエティ！</desc>
		<icon src="https://statics.tver.jp/images/content/thumbnail/live/xlarge/lexzdeylyw.jpg?v=553cc0fe" />
	</programme>
	<programme channel="ex" start="20260401125400 +0000" stop="20260401141000 +0000">
		<title>報道ステーション</title>
		<desc>「深く、力強く、きょう色々。」大越健介キャスターが、きょう知りたいニュースを“深い洞察”と“平たい言葉”でお送りします。</desc>
		<icon src="https://statics.tver.jp/images/content/thumbnail/live/xlarge/lebh5sqhg2.jpg?v=2528e40c" />
	</programme>
	<programme channel="ex" start="20260402125400 +0000" stop="20260402141000 +0000">
		<title>報道ステーション</title>
		<desc>「深く、力強く、きょう色々。」大越健介キャスターが、きょう知りたいニュースを“深い洞察”と“平たい言葉”でお送りします。</desc>
		<icon src="https://statics.tver.jp/images/content/thumbnail/live/xlarge/le4vji8yd6.jpg?v=fd21ba94" />
	</programme>
	<programme channel="tbs" start="20260320115500 +0000" stop="20260320130000 +0000">
		<title>黄金のワンスプーン！</title>
		<desc>舘様のレストランに及川光博・M!LK佐野&amp;塩﨑・山田優が来店</desc>
		<icon src="https://statics.tver.jp/images/content/thumbnail/live/xlarge/le4ri78k2a.jpg?v=99fdff11" />
	</programme>
	<programme channel="tbs" start="20260320130000 +0000" stop="20260320135400 +0000">
		<title>今、知っておきたい！！界隈グルメ</title>
		<desc>花見にぴったりパン祭り！“サンドイッチ界隈”</desc>
		<icon src="https://statics.tver.jp/images/content/thumbnail/live/xlarge/letj1msqyc.jpg?v=84d550a8" />
	</programme>
	<programme channel="tbs" start="20260320135400 +0000" stop="20260320194500 +0000">
		<title>配信休止</title>
		<desc>配信休止</desc>
		<icon src="https://statics.tver.jp/images/content/thumbnail/live/xlarge/levmj8946l.jpg?v=8668fb5d" />
	</programme>
	<programme channel="tbs" start="20260320194500 +0000" stop="20260321095100 +0000">
		<title>配信休止</title>
		<desc>配信休止</desc>
		<icon src="https://statics.tver.jp/images/content/thumbnail/live/xlarge/lef1bcyelr.jpg?v=f0c31b48" />
	</programme>
	<programme channel="tbs" start="20260321095100 +0000" stop="20260321115400 +0000">
		<title>熱狂マニアさん！</title>
		<desc>＜配信は19時から＞コンビニｖｓスーパー！３キロ痩せるには何日間？春の３大検証ＳＰ</desc>
		<icon src="https://statics.tver.jp/images/content/thumbnail/live/xlarge/let9r8vqpy.jpg?v=d30aba33" />
	</programme>
	<programme channel="tbs" start="20260321115400 +0000" stop="20260321125600 +0000">
		<title>いくらかわかる金？</title>
		<desc>春の房総・人気浜焼き店で爆食＆高得点で賞金！デュエットカラオケ</desc>
		<icon src="https://statics.tver.jp/images/content/thumbnail/live/xlarge/le9u1d9zxv.jpg?v=853ed5bd" />
	</programme>
	<programme channel="tbs" start="20260321125600 +0000" stop="20260321194000 +0000">
		<title>配信休止</title>
		<desc>配信休止</desc>
		<icon src="https://statics.tver.jp/images/content/thumbnail/live/xlarge/lelh4t40gn.jpg?v=97922c2b" />
	</programme>
	<programme channel="tbs" start="20260321194000 +0000" stop="20260322100000 +0000">
		<title>配信休止</title>
		<desc>配信休止</desc>
		<icon src="https://statics.tver.jp/images/content/thumbnail/live/xlarge/le8cjlyx3c.jpg?v=5c1d75c9" />
	</programme>
	<programme channel="tbs" start="20260322100000 +0000" stop="20260322120000 +0000">
		<title>バナナマンのせっかくグルメ!!</title>
		<desc>福岡＆金沢＆新潟＆横須賀で日村・眞栄田郷敦が爆食</desc>
		<icon src="https://statics.tver.jp/images/content/thumbnail/live/xlarge/lezsq5bsna.jpg?v=bbaf37d7" />
	</programme>
	<programme channel="tbs" start="20260322120000 +0000" stop="20260322125400 +0000">
		<title>リブート</title>
		<desc>第九話「夫婦」</desc>
		<icon src="https://statics.tver.jp/images/content/thumbnail/live/xlarge/letd01hpg0.jpg?v=a7faa40a" />
	</programme>
	<programme channel="tbs" start="20260322125400 +0000" stop="20260322130000 +0000">
		<title>お知らせ</title>
		<desc>リアルタイム配信予定の番組は「TBS系」タブよりご確認いただけます。</desc>
		<icon src="https://statics.tver.jp/images/content/thumbnail/live/xlarge/legikmnjt8.jpg?v=a4eb86e3" />
	</programme>
	<programme channel="tbs" start="20260322130000 +0000" stop="20260322135400 +0000">
		<title>日曜日の初耳学</title>
		<desc>【Mr.Children桜井和寿に林先生が…2時間半のロングインタビュー！】</desc>
		<icon src="https://statics.tver.jp/images/content/thumbnail/live/xlarge/ledai6doph.jpg?v=856eadd2" />
	</programme>
	<programme channel="tbs" start="20260322135400 +0000" stop="20260322140000 +0000">
		<title>お知らせ</title>
		<desc>リアルタイム配信予定の番組は「TBS系」タブよりご確認いただけます。</desc>
		<icon src="https://statics.tver.jp/images/content/thumbnail/live/xlarge/lejldwtr7o.jpg?v=8894dc61" />
	</programme>
	<programme channel="tbs" start="20260322140000 +0000" stop="20260322143000 +0000">
		<title>情熱大陸</title>
		<desc>【安發伸太郎／フレンチシェフ▽パリが誇る三つ星を託された日本人シェフ】</desc>
		<icon src="https://statics.tver.jp/images/content/thumbnail/live/xlarge/le1y3xpgx2.jpg?v=bcded267" />
	</programme>
	<programme channel="tbs" start="20260322143000 +0000" stop="20260322193000 +0000">
		<title>配信休止</title>
		<desc>配信休止</desc>
		<icon src="https://statics.tver.jp/images/content/thumbnail/live/xlarge/lejtatlee1.jpg?v=b32c3eeb" />
	</programme>
	<programme channel="tbs" start="20260322193000 +0000" stop="20260322230000 +0000">
		<title>配信休止</title>
		<desc>配信休止</desc>
		<icon src="https://statics.tver.jp/images/content/thumbnail/live/xlarge/lejgku2ed7.jpg?v=9917b7fa" />
	</programme>
	<programme channel="tbs" start="20260322230000 +0000" stop="20260323005500 +0000">
		<title>ラヴィット！</title>
		<desc>【5周年ウィークスタート！リクエストに応えヒヤシンス再結集!?】</desc>
		<icon src="https://statics.tver.jp/images/content/thumbnail/live/xlarge/lep91jxp00.jpg?v=fda421be" />
	</programme>
	<programme channel="tbs" start="20260323005500 +0000" stop="20260323100000 +0000">
		<title>配信休止</title>
		<desc>配信休止</desc>
		<icon src="https://statics.tver.jp/images/content/thumbnail/live/xlarge/le7z2t9c35.jpg?v=797ba402" />
	</programme>
	<programme channel="tbs" start="20260323100000 +0000" stop="20260323125400 +0000">
		<title>MUSOU</title>
		<desc>TBSアトラクションバラエティの集大成★MUSOU</desc>
		<icon src="https://statics.tver.jp/images/content/thumbnail/live/xlarge/le8knbwnd7.jpg?v=8bc92b10" />
	</programme>
	<programme channel="tbs" start="20260323125400 +0000" stop="20260323135700 +0000">
		<title>サンドウィッチマンの世界ほぼゼロ生き物ハンター</title>
		<desc>サンドウィッチマンの世界ほぼゼロ生き物ハンター</desc>
		<icon src="https://statics.tver.jp/images/content/thumbnail/live/xlarge/lel7o4r4t0.jpg?v=b967c2a8" />
	</programme>
	<programme channel="tbs" start="20260323135700 +0000" stop="20260323193000 +0000">
		<title>配信休止</title>
		<desc>配信休止</desc>
		<icon src="https://statics.tver.jp/images/content/thumbnail/live/xlarge/lemzhqqr3q.jpg?v=608d70fe" />
	</programme>
	<programme channel="tbs" start="20260323193000 +0000" stop="20260323230000 +0000">
		<title>配信休止</title>
		<desc>配信休止</desc>
		<icon src="https://statics.tver.jp/images/content/thumbnail/live/xlarge/lekcn46lfu.jpg?v=b995df35" />
	</programme>
	<programme channel="tbs" start="20260323230000 +0000" stop="20260324005500 +0000">
		<title>ラヴィット！</title>
		<desc>【かまいたち＆本田望結・紗来＆ちょんまげ登場▼逆ババ抜き王決定戦】</desc>
		<icon src="https://statics.tver.jp/images/content/thumbnail/live/xlarge/lean3n8gi9.jpg?v=c57e4025" />
	</programme>
	<programme channel="tbs" start="20260324005500 +0000" stop="20260324100000 +0000">
		<title>配信休止</title>
		<desc>配信休止</desc>
		<icon src="https://statics.tver.jp/images/content/thumbnail/live/xlarge/lentd84kos.jpg?v=97e077df" />
	</programme>
	<programme channel="tbs" start="20260324100000 +0000" stop="20260324110000 +0000">
		<title>THE神業チャレンジ</title>
		<desc>山田裕貴&amp;綾野剛VS神フェイク！アスリートVS１００秒神業</desc>
		<icon src="https://statics.tver.jp/images/content/thumbnail/live/xlarge/leewfpubeu.jpg?v=535928d1" />
	</programme>
	<programme channel="tbs" start="20260324110000 +0000" stop="20260324115500 +0000">
		<title>バナナサンド</title>
		<desc>はいだしょうこお姉さん＆横山だいすけお兄さんがハモリ我慢SP</desc>
		<icon src="https://statics.tver.jp/images/content/thumbnail/live/xlarge/lebi6tdtc2.jpg?v=95593ebf" />
	</programme>
	<programme channel="tbs" start="20260324115500 +0000" stop="20260324130000 +0000">
		<title>マツコの知らない世界</title>
		<desc>春らんまんSP!桜と楽しむ最新和菓子36連発▼SNSバズる!空港絶景</desc>
		<icon src="https://statics.tver.jp/images/content/thumbnail/live/xlarge/le8xiwz0zc.jpg?v=e209982b" />
	</programme>
	<programme channel="tbs" start="20260324130000 +0000" stop="20260324140000 +0000">
		<title>未来のムスコ</title>
		<desc>最終話　ついに完結！明かされるムスコの秘密——</desc>
		<icon src="https://statics.tver.jp/images/content/thumbnail/live/xlarge/le1cbpp8fc.jpg?v=ce8ea969" />
	</programme>
	<programme channel="tbs" start="20260324140000 +0000" stop="20260324193000 +0000">
		<title>配信休止</title>
		<desc>配信休止</desc>
		<icon src="https://statics.tver.jp/images/content/thumbnail/live/xlarge/lek6fsybhj.jpg?v=322c5aa1" />
	</programme>
	<programme channel="tbs" start="20260324193000 +0000" stop="20260324230000 +0000">
		<title>配信休止</title>
		<desc>配信休止</desc>
		<icon src="https://statics.tver.jp/images/content/thumbnail/live/xlarge/le6bhkk6s7.jpg?v=e35ac773" />
	</programme>
	<programme channel="tbs" start="20260324230000 +0000" stop="20260325005500 +0000">
		<title>ラヴィット！</title>
		<desc>THEジャスト2時間SP！</desc>
		<icon src="https://statics.tver.jp/images/content/thumbnail/live/xlarge/lefqk2rkvh.jpg?v=a76bcf7a" />
	</programme>
	<programme channel="tbs" start="20260325005500 +0000" stop="20260325125800 +0000">
		<title>配信休止</title>
		<desc>配信休止</desc>
		<icon src="https://statics.tver.jp/images/content/thumbnail/live/xlarge/leyoigdodt.jpg?v=37b98cc8" />
	</programme>
	<programme channel="tbs" start="20260325125800 +0000" stop="20260325130000 +0000">
		<title>お知らせ</title>
		<desc>リアルタイム配信予定の番組は「TBS系」タブよりご確認いただけます。</desc>
		<icon src="https://statics.tver.jp/images/content/thumbnail/live/xlarge/leuwyipom5.jpg?v=e2727afc" />
	</programme>
	<programme channel="tbs" start="20260325130000 +0000" stop="20260325135700 +0000">
		<title>水曜日のダウンタウン</title>
		<desc>芸能人が持ち寄った“説”を検証</desc>
		<icon src="https://statics.tver.jp/images/content/thumbnail/live/xlarge/lekumugzfh.jpg?v=539cd772" />
	</programme>
	<programme channel="tbs" start="20260325135700 +0000" stop="20260325193000 +0000">
		<title>配信休止</title>
		<desc>配信休止</desc>
		<icon src="https://statics.tver.jp/images/content/thumbnail/live/xlarge/leumqhc77p.jpg?v=8dfe0ecb" />
	</programme>
	<programme channel="tbs" start="20260325193000 +0000" stop="20260325230000 +0000">
		<title>配信休止</title>
		<desc>配信休止</desc>
		<icon src="https://statics.tver.jp/images/content/thumbnail/live/xlarge/le1ifeurkr.jpg?v=f260c348" />
	</programme>
	<programme channel="tbs" start="20260325230000 +0000" stop="20260326005500 +0000">
		<title>ラヴィット！</title>
		<desc>世界的革命家・西野亮廣が降臨！日本の朝に再び伝説を残せるか！？</desc>
		<icon src="https://statics.tver.jp/images/content/thumbnail/live/xlarge/leccwkpcar.jpg?v=e1db8f0e" />
	</programme>
	<programme channel="tbs" start="20260326005500 +0000" stop="20260326100000 +0000">
		<title>配信休止</title>
		<desc>配信休止</desc>
		<icon src="https://statics.tver.jp/images/content/thumbnail/live/xlarge/lejuhcmkrk.jpg?v=c597f90e" />
	</programme>
	<programme channel="tbs" start="20260326100000 +0000" stop="20260326115800 +0000">
		<title>クイズ！昭和１００年プラス</title>
		<desc>◆村上信五MC★昭和〜平成令和を１年１問！アナタも挑戦</desc>
		<icon src="https://statics.tver.jp/images/content/thumbnail/live/xlarge/leoybdhbsl.jpg?v=f64689a3" />
	</programme>
	<programme channel="tbs" start="20260326115800 +0000" stop="20260326140000 +0000">
		<title>ちるらん 新撰組鎮魂歌</title>
		<desc>〜江戸青春篇〜 第１夜</desc>
		<icon src="https://statics.tver.jp/images/content/thumbnail/live/xlarge/ler4czerh2.jpg?v=02c2fdfe" />
	</programme>
	<programme channel="tbs" start="20260326140000 +0000" stop="20260326193000 +0000">
		<title>配信休止</title>
		<desc>配信休止</desc>
		<icon src="https://statics.tver.jp/images/content/thumbnail/live/xlarge/le0if8z7jh.jpg?v=1520ca25" />
	</programme>
	<programme channel="tbs" start="20260326193000 +0000" stop="20260326230000 +0000">
		<title>配信休止</title>
		<desc>配信休止</desc>
		<icon src="https://statics.tver.jp/images/content/thumbnail/live/xlarge/leq4rb96id.jpg?v=a13bd07d" />
	</programme>
	<programme channel="tbs" start="20260326230000 +0000" stop="20260327005500 +0000">
		<title>ラヴィット！</title>
		<desc>【５周年ウィーク最終日！サンボSPライブ開催▼川島兄弟＆川島明王】</desc>
		<icon src="https://statics.tver.jp/images/content/thumbnail/live/xlarge/lem502ro7t.jpg?v=d14ecd63" />
	</programme>
	<programme channel="tbs" start="20260327005500 +0000" stop="20260327100000 +0000">
		<title>配信休止</title>
		<desc>配信休止</desc>
		<icon src="https://statics.tver.jp/images/content/thumbnail/live/xlarge/leq75xpwnu.jpg?v=f32dc13f" />
	</programme>
	<programme channel="tbs" start="20260327100000 +0000" stop="20260327115700 +0000">
		<title>「オオカミ少年」特別版『スポッパ』</title>
		<desc>「オオカミ少年」特別版★スポッパ</desc>
		<icon src="https://statics.tver.jp/images/content/thumbnail/live/xlarge/le240zj32b.jpg?v=b2e5f601" />
	</programme>
	<programme channel="tbs" start="20260327115700 +0000" stop="20260327135400 +0000">
		<title>ちるらん 新撰組鎮魂歌</title>
		<desc>〜江戸青春篇〜 第２夜</desc>
		<icon src="https://statics.tver.jp/images/content/thumbnail/live/xlarge/leec92hwol.jpg?v=111a312d" />
	</programme>
	<programme channel="tbs" start="20260327135400 +0000" stop="20260327194500 +0000">
		<title>配信休止</title>
		<desc>配信休止</desc>
		<icon src="https://statics.tver.jp/images/content/thumbnail/live/xlarge/lemturgkm9.jpg?v=ecf0d171" />
	</programme>
	<programme channel="tbs" start="20260327194500 +0000" stop="20260328095100 +0000">
		<title>配信休止</title>
		<desc>配信休止</desc>
		<icon src="https://statics.tver.jp/images/content/thumbnail/live/xlarge/le2cg7v16u.jpg?v=0bb6e5e0" />
	</programme>
	<programme channel="tbs" start="20260328095100 +0000" stop="20260328115400 +0000">
		<title>ジョブチューン ～アノ職業のヒミツぶっちゃけます！</title>
		<desc>＜配信は19時から＞イオントップバリュ×超一流料理人！ワンコイン以下10品ジャッジ</desc>
		<icon src="https://statics.tver.jp/images/content/thumbnail/live/xlarge/ley31c8ayr.jpg?v=f383bc96" />
	</programme>
	<programme channel="tbs" start="20260328115400 +0000" stop="20260328125600 +0000">
		<title>いくらかわかる金？</title>
		<desc>水戸の人気飲み屋街で関太＆関取が爆食！陸上選手から逃げれば賞金</desc>
		<icon src="https://statics.tver.jp/images/content/thumbnail/live/xlarge/lewpxyia6n.jpg?v=bed06376" />
	</programme>
	<programme channel="tbs" start="20260328125600 +0000" stop="20260328200000 +0000">
		<title>配信休止</title>
		<desc>配信休止</desc>
		<icon src="https://statics.tver.jp/images/content/thumbnail/live/xlarge/le3lm1k50v.jpg?v=0b5a56b3" />
	</programme>
	<programme channel="tbs" start="20260328200000 +0000" stop="20260329100000 +0000">
		<title>配信休止</title>
		<desc>配信休止</desc>
		<icon src="https://statics.tver.jp/images/content/thumbnail/live/xlarge/leiy7v1hng.jpg?v=70876bcf" />
	</programme>
	<programme channel="tbs" start="20260329100000 +0000" stop="20260329120000 +0000">
		<title>坂上&amp;指原のつぶれない店</title>
		<desc>ファミマおにぎりの超（秘）製法＆韓国コスメ!?さゆりんご復活</desc>
		<icon src="https://statics.tver.jp/images/content/thumbnail/live/xlarge/lefj0ve9zk.jpg?v=7f17260f" />
	</programme>
	<programme channel="tbs" start="20260329120000 +0000" stop="20260329131400 +0000">
		<title>リブート</title>
		<desc>第十話「再起動」</desc>
		<icon src="https://statics.tver.jp/images/content/thumbnail/live/xlarge/lejywxs4h0.jpg?v=05ef873f" />
	</programme>
	<programme channel="tbs" start="20260329131400 +0000" stop="20260329132000 +0000">
		<title>お知らせ</title>
		<desc>リアルタイム配信予定の番組は「TBS系」タブよりご確認いただけます。</desc>
		<icon src="https://statics.tver.jp/images/content/thumbnail/live/xlarge/lea7yi9cxs.jpg?v=49c149a8" />
	</programme>
	<programme channel="tbs" start="20260329132000 +0000" stop="20260329141400 +0000">
		<title>日曜日の初耳学</title>
		<desc>【超貴重！２週連続 Mr.Children 桜井和寿×林修 スペシャル完結編】</desc>
		<icon src="https://statics.tver.jp/images/content/thumbnail/live/xlarge/le5wldqqka.jpg?v=761fa297" />
	</programme>
	<programme channel="tbs" start="20260329141400 +0000" stop="20260329142000 +0000">
		<title>お知らせ</title>
		<desc>リアルタイム配信予定の番組は「TBS系」タブよりご確認いただけます。</desc>
		<icon src="https://statics.tver.jp/images/content/thumbnail/live/xlarge/le8awop63y.jpg?v=20a31aa0" />
	</programme>
	<programme channel="tbs" start="20260329142000 +0000" stop="20260329145000 +0000">
		<title>情熱大陸</title>
		<desc>【生見愛瑠／モデル・俳優▽口癖は「何も考えてない」!?“めるる”の実像】</desc>
		<icon src="https://statics.tver.jp/images/content/thumbnail/live/xlarge/lebh98vkoo.jpg?v=eee7a1ee" />
	</programme>
	<programme channel="tbs" start="20260329145000 +0000" stop="20260329193000 +0000">
		<title>配信休止</title>
		<desc>配信休止</desc>
		<icon src="https://statics.tver.jp/images/content/thumbnail/live/xlarge/le8la3mbnr.jpg?v=40002909" />
	</programme>
	<programme channel="tbs" start="20260329193000 +0000" stop="20260329230000 +0000">
		<title>配信休止</title>
		<desc>配信休止</desc>
		<icon src="https://statics.tver.jp/images/content/thumbnail/live/xlarge/le6t8n8vzh.jpg?v=1a01bcde" />
	</programme>
	<programme channel="tbs" start="20260329230000 +0000" stop="20260330005500 +0000">
		<title>ラヴィット！</title>
		<desc>▼６年目も日本一明るい朝を！！▼シャトレーゼ売り上げトップ１０は？</desc>
		<icon src="https://statics.tver.jp/images/content/thumbnail/live/xlarge/leewkn1uqn.jpg?v=a07944ee" />
	</programme>
	<programme channel="tbs" start="20260330005500 +0000" stop="20260330100000 +0000">
		<title>配信休止</title>
		<desc>配信休止</desc>
		<icon src="https://statics.tver.jp/images/content/thumbnail/live/xlarge/lenjnqr0pj.jpg?v=17df3773" />
	</programme>
	<programme channel="tbs" start="20260330100000 +0000" stop="20260330135700 +0000">
		<title>CDTV ライブ! ライブ!</title>
		<desc>春の4時間SP★Mr.Children★King Gnu</desc>
		<icon src="https://statics.tver.jp/images/content/thumbnail/live/xlarge/lezrffdj6r.jpg?v=adc9ecab" />
	</programme>
	<programme channel="tbs" start="20260330135700 +0000" stop="20260330193000 +0000">
		<title>配信休止</title>
		<desc>配信休止</desc>
		<icon src="https://statics.tver.jp/images/content/thumbnail/live/xlarge/lel4gc9at9.jpg?v=842cf141" />
	</programme>
	<programme channel="tbs" start="20260330193000 +0000" stop="20260330230000 +0000">
		<title>配信休止</title>
		<desc>配信休止</desc>
		<icon src="https://statics.tver.jp/images/content/thumbnail/live/xlarge/lemymfjy6v.jpg?v=d8dc363a" />
	</programme>
	<programme channel="tbs" start="20260330230000 +0000" stop="20260331005500 +0000">
		<title>ラヴィット！</title>
		<desc>日本でいちばん明るい朝番組</desc>
		<icon src="https://statics.tver.jp/images/content/thumbnail/live/xlarge/le2vsvhndm.jpg?v=95802552" />
	</programme>
	<programme channel="tbs" start="20260331005500 +0000" stop="20260331100000 +0000">
		<title>配信休止</title>
		<desc>配信休止</desc>
		<icon src="https://statics.tver.jp/images/content/thumbnail/live/xlarge/le1ilmi5aq.jpg?v=ccb84713" />
	</programme>
	<programme channel="tbs" start="20260331100000 +0000" stop="20260331115500 +0000">
		<title>THE神業チャレンジ</title>
		<desc>東京ディズニーリゾート神キャストVS芸能人&amp;創作寿司対決！</desc>
		<icon src="https://statics.tver.jp/images/content/thumbnail/live/xlarge/leva243wf5.jpg?v=f524b159" />
	</programme>
	<programme channel="tbs" start="20260331115500 +0000" stop="20260331130000 +0000">
		<title>マツコの知らない世界</title>
		<desc>劇的進化・北関東ホームセンターSPネット販売に負けない独自戦略</desc>
		<icon src="https://statics.tver.jp/images/content/thumbnail/live/xlarge/leqh7q97rt.jpg?v=c24b5f1f" />
	</programme>
	<programme channel="tbs" start="20260331130000 +0000" stop="20260331140000 +0000">
		<title>6SixTONES</title>
		<desc>松たか子・向井理・亀梨和也・チョコプラ！豪華芸能人お祝いSP</desc>
		<icon src="https://statics.tver.jp/images/content/thumbnail/live/xlarge/lepkm0k2r5.jpg?v=f101633a" />
	</programme>
	<programme channel="tbs" start="20260331140000 +0000" stop="20260331193000 +0000">
		<title>配信休止</title>
		<desc>配信休止</desc>
		<icon src="https://statics.tver.jp/images/content/thumbnail/live/xlarge/leay6qyl0a.jpg?v=36114713" />
	</programme>
	<programme channel="tbs" start="20260331193000 +0000" stop="20260331230000 +0000">
		<title>配信休止</title>
		<desc>配信休止</desc>
		<icon src="https://statics.tver.jp/images/content/thumbnail/live/xlarge/le1awzypdf.jpg?v=0be57582" />
	</programme>
	<programme channel="tbs" start="20260331230000 +0000" stop="20260401005500 +0000">
		<title>ラヴィット！</title>
		<desc>日本でいちばん明るい朝番組</desc>
		<icon src="https://statics.tver.jp/images/content/thumbnail/live/xlarge/lesuamjsk5.jpg?v=cc170e3b" />
	</programme>
	<programme channel="tbs" start="20260401005500 +0000" stop="20260401125800 +0000">
		<title>配信休止</title>
		<desc>配信休止</desc>
		<icon src="https://statics.tver.jp/images/content/thumbnail/live/xlarge/lefxlg2ywf.jpg?v=769186fd" />
	</programme>
	<programme channel="tbs" start="20260401125800 +0000" stop="20260401130000 +0000">
		<title>お知らせ</title>
		<desc>リアルタイム配信予定の番組は「TBS系」タブよりご確認いただけます。</desc>
		<icon src="https://statics.tver.jp/images/content/thumbnail/live/xlarge/le952dyqea.jpg?v=83608f7a" />
	</programme>
	<programme channel="tbs" start="20260401130000 +0000" stop="20260401135700 +0000">
		<title>水曜日のダウンタウン</title>
		<desc>芸能人が持ち寄った“説”を検証</desc>
		<icon src="https://statics.tver.jp/images/content/thumbnail/live/xlarge/lehdn4bpxy.jpg?v=c43d10c3" />
	</programme>
	<programme channel="tbs" start="20260401135700 +0000" stop="20260401193000 +0000">
		<title>配信休止</title>
		<desc>配信休止</desc>
		<icon src="https://statics.tver.jp/images/content/thumbnail/live/xlarge/lej0ncrs3g.jpg?v=297b48be" />
	</programme>
	<programme channel="tbs" start="20260401193000 +0000" stop="20260401230000 +0000">
		<title>配信休止</title>
		<desc>配信休止</desc>
		<icon src="https://statics.tver.jp/images/content/thumbnail/live/xlarge/le4vp8l1gu.jpg?v=e009af27" />
	</programme>
	<programme channel="tbs" start="20260401230000 +0000" stop="20260402005500 +0000">
		<title>ラヴィット！</title>
		<desc>日本でいちばん明るい朝番組</desc>
		<icon src="https://statics.tver.jp/images/content/thumbnail/live/xlarge/lepxgt4t6s.jpg?v=1c42de1e" />
	</programme>
	<programme channel="tbs" start="20260402005500 +0000" stop="20260402100000 +0000">
		<title>配信休止</title>
		<desc>配信休止</desc>
		<icon src="https://statics.tver.jp/images/content/thumbnail/live/xlarge/le22cesdpo.jpg?v=edc24f60" />
	</programme>
	<programme channel="tbs" start="20260402100000 +0000" stop="20260402130000 +0000">
		<title>ニンゲン観察バラエティ モニタリング</title>
		<desc>ニンゲン観察モニタリングSP★DA PUMPが突然現れライブをしたら？</desc>
		<icon src="https://statics.tver.jp/images/content/thumbnail/live/xlarge/leqe2hwpty.jpg?v=9ddf8ccd" />
	</programme>
	<programme channel="tbs" start="20260402130000 +0000" stop="20260402135700 +0000">
		<title>櫻井･有吉THE夜会</title>
		<desc>櫻井翔・有吉弘行がお届けする大人のバラエティ</desc>
		<icon src="https://statics.tver.jp/images/content/thumbnail/live/xlarge/le3x3irwmm.jpg?v=2c6430f2" />
	</programme>
	<programme channel="tbs" start="20260402135700 +0000" stop="20260402193000 +0000">
		<title>配信休止</title>
		<desc>配信休止</desc>
		<icon src="https://statics.tver.jp/images/content/thumbnail/live/xlarge/letsl0mype.jpg?v=106c1d22" />
	</programme>
	<programme channel="tbs" start="20260402193000 +0000" stop="20260402230000 +0000">
		<title>配信休止</title>
		<desc>配信休止</desc>
		<icon src="https://statics.tver.jp/images/content/thumbnail/live/xlarge/le2iy19uwj.jpg?v=4877c5a4" />
	</programme>
	<programme channel="tbs" start="20260402230000 +0000" stop="20260403005500 +0000">
		<title>ラヴィット！</title>
		<desc>日本でいちばん明るい朝番組</desc>
		<icon src="https://statics.tver.jp/images/content/thumbnail/live/xlarge/leu22fiukg.jpg?v=107b0afb" />
	</programme>
	<programme channel="tbs" start="20260403005500 +0000" stop="20260403100000 +0000">
		<title>配信休止</title>
		<desc>配信休止</desc>
		<icon src="https://statics.tver.jp/images/content/thumbnail/live/xlarge/lewq5k8n3w.jpg?v=3e8dbc6c" />
	</programme>
	<programme channel="tbs" start="20260403100000 +0000" stop="20260403130000 +0000">
		<title>それSnow Manにやらせて下さい</title>
		<desc>それＳｎｏｗ　Ｍａｎにやらせて下さいＳＰ</desc>
		<icon src="https://statics.tver.jp/images/content/thumbnail/live/xlarge/lee29ucvua.jpg?v=d21bda8a" />
	</programme>
	<programme channel="tx" start="20260320102500 +0000" stop="20260320125400 +0000">
		<title>所さんの学校では教えてくれないそこんトコロ！</title>
		<desc>所さんのそこんトコロ【秘境アマゾン&amp;史上最高開かずの金庫！怒涛の２時間半SP】</desc>
		<icon src="https://statics.tver.jp/images/content/thumbnail/live/xlarge/leomknpkvy.jpg?v=cf07684b" />
	</programme>
	<programme channel="tx" start="20260320125400 +0000" stop="20260320130000 +0000">
		<title>配信準備中</title>
		<desc>配信準備中</desc>
		<icon src="https://statics.tver.jp/images/content/thumbnail/live/xlarge/lensony0ss.jpg?v=2c7900c3" />
	</programme>
	<programme channel="tx" start="20260320130000 +0000" stop="20260320135400 +0000">
		<title>ガイアの夜明け</title>
		<desc>ガイアの夜明け【あの主人公はいま…3.11SP故郷を取り戻す！】</desc>
		<icon src="https://statics.tver.jp/images/content/thumbnail/live/xlarge/lezsgcvryq.jpg?v=4e2f18bf" />
	</programme>
	<programme channel="tx" start="20260320135400 +0000" stop="20260320140000 +0000">
		<title>配信準備中</title>
		<desc>配信準備中</desc>
		<icon src="https://statics.tver.jp/images/content/thumbnail/live/xlarge/le5reibkof.jpg?v=c43169a5" />
	</programme>
	<programme channel="tx" start="20260320140000 +0000" stop="20260320145800 +0000">
		<title>ＷＢＳ（ワールドビジネスサテライト）</title>
		<desc>ＷＢＳ　日米首脳会談を詳報！イラン、対米投資、レアアース、注目３テーマを分析！</desc>
		<icon src="https://statics.tver.jp/images/content/thumbnail/live/xlarge/le6t91v9qh.jpg?v=71634e75" />
	</programme>
	<programme channel="tx" start="20260320145800 +0000" stop="20260320190000 +0000">
		<title>配信準備中</title>
		<desc>配信準備中</desc>
		<icon src="https://statics.tver.jp/images/content/thumbnail/live/xlarge/le9pm5h4p4.jpg?v=575152d1" />
	</programme>
	<programme channel="tx" start="20260320190000 +0000" stop="20260321093000 +0000">
		<title>配信準備中</title>
		<desc>配信準備中</desc>
		<icon src="https://statics.tver.jp/images/content/thumbnail/live/xlarge/lew7ebkv4l.jpg?v=b107249a" />
	</programme>
	<programme channel="tx" start="20260321093000 +0000" stop="20260321115500 +0000">
		<title>土曜ゴールデン</title>
		<desc>土曜ゴールデンあさこ・梨乃の５万円旅　絶景の瀬戸内うまい酒に乾杯ＳＰ山口広島</desc>
		<icon src="https://statics.tver.jp/images/content/thumbnail/live/xlarge/lemaqpb93f.jpg?v=82d9fd54" />
	</programme>
	<programme channel="tx" start="20260321115500 +0000" stop="20260321120000 +0000">
		<title>配信準備中</title>
		<desc>配信準備中</desc>
		<icon src="https://statics.tver.jp/images/content/thumbnail/live/xlarge/lefouej5su.jpg?v=49937f1a" />
	</programme>
	<programme channel="tx" start="20260321120000 +0000" stop="20260321130900 +0000">
		<title>出没！アド街ック天国</title>
		<desc>出没！アド街ック天国【お茶の水】４月からの新生活で大賑わい♪日本最大級の学生街</desc>
		<icon src="https://statics.tver.jp/images/content/thumbnail/live/xlarge/ledm5hctyt.jpg?v=d17a94b1" />
	</programme>
	<programme channel="tx" start="20260321130900 +0000" stop="20260321190000 +0000">
		<title>配信準備中</title>
		<desc>配信準備中</desc>
		<icon src="https://statics.tver.jp/images/content/thumbnail/live/xlarge/le0eeqdsox.jpg?v=ce5b83b1" />
	</programme>
	<programme channel="tx" start="20260321190000 +0000" stop="20260322093000 +0000">
		<title>配信準備中</title>
		<desc>配信準備中</desc>
		<icon src="https://statics.tver.jp/images/content/thumbnail/live/xlarge/letdc4la33.jpg?v=daa17314" />
	</programme>
	<programme channel="tx" start="20260322093000 +0000" stop="20260322115000 +0000">
		<title>ウソかホントかわからない やりすぎ都市伝説</title>
		<desc>ウソかホントかわからない“やりすぎ都市伝説2026春”身近に潜む都市伝説35連発！</desc>
		<icon src="https://statics.tver.jp/images/content/thumbnail/live/xlarge/lewvvrn9y6.jpg?v=6ab98b2f" />
	</programme>
	<programme channel="tx" start="20260322115000 +0000" stop="20260322125400 +0000">
		<title>家、ついて行ってイイですか？</title>
		<desc>家、ついて行ってイイですか？桜の木の下で「来世も一緒に…」闘病妻と夫の涙の物語</desc>
		<icon src="https://statics.tver.jp/images/content/thumbnail/live/xlarge/leq9firnir.jpg?v=9c6c840c" />
	</programme>
	<programme channel="tx" start="20260322125400 +0000" stop="20260322130000 +0000">
		<title>配信準備中</title>
		<desc>配信準備中</desc>
		<icon src="https://statics.tver.jp/images/content/thumbnail/live/xlarge/lewfxybov4.jpg?v=84952111" />
	</programme>
	<programme channel="tx" start="20260322130000 +0000" stop="20260322144300 +0000">
		<title>すっかり　にちようチャップリン</title>
		<desc>すっかり　にちようチャップリンＳＰ【新ネタだけの賞レース】王者に輝くのは！？</desc>
		<icon src="https://statics.tver.jp/images/content/thumbnail/live/xlarge/leoo6urvp1.jpg?v=c1250dad" />
	</programme>
	<programme channel="tx" start="20260322144300 +0000" stop="20260322190000 +0000">
		<title>配信準備中</title>
		<desc>配信準備中</desc>
		<icon src="https://statics.tver.jp/images/content/thumbnail/live/xlarge/lei5hovv0y.jpg?v=ec735cbe" />
	</programme>
	<programme channel="tx" start="20260322190000 +0000" stop="20260323092500 +0000">
		<title>配信準備中</title>
		<desc>配信準備中</desc>
		<icon src="https://statics.tver.jp/images/content/thumbnail/live/xlarge/lezdtez14g.jpg?v=df146d77" />
	</programme>
	<programme channel="tx" start="20260323092500 +0000" stop="20260323110000 +0000">
		<title>YOUは何しに日本へ？</title>
		<desc>ＹＯＵは何しに日本へ？★パスポート紛失で奇跡の旅＆超厳しい！和食の登竜門に挑む</desc>
		<icon src="https://statics.tver.jp/images/content/thumbnail/live/xlarge/ley4txu6f9.jpg?v=7e96180e" />
	</programme>
	<programme channel="tx" start="20260323110000 +0000" stop="20260323130900 +0000">
		<title>世界！ニッポン行きたい人応援団</title>
		<desc>世界！ニッポン行きたい人応援団★世界が愛した国民食ＳＰ！お好み焼き＆究極弁当</desc>
		<icon src="https://statics.tver.jp/images/content/thumbnail/live/xlarge/lekd7ihgeq.jpg?v=9b302ff2" />
	</programme>
	<programme channel="tx" start="20260323130900 +0000" stop="20260323131500 +0000">
		<title>配信準備中</title>
		<desc>配信準備中</desc>
		<icon src="https://statics.tver.jp/images/content/thumbnail/live/xlarge/le9cgdb5yi.jpg?v=e4c62e82" />
	</programme>
	<programme channel="tx" start="20260323131500 +0000" stop="20260323141300 +0000">
		<title>ＷＢＳ（ワールドビジネスサテライト）</title>
		<desc>ＷＢＳ　トランプ氏”期限”まで10時間ほど何が起きる▽中東危機でバナナがピンチ？</desc>
		<icon src="https://statics.tver.jp/images/content/thumbnail/live/xlarge/lez3hl85cu.jpg?v=f0782b44" />
	</programme>
	<programme channel="tx" start="20260323141300 +0000" stop="20260323190000 +0000">
		<title>配信準備中</title>
		<desc>配信準備中</desc>
		<icon src="https://statics.tver.jp/images/content/thumbnail/live/xlarge/lersjmdzta.jpg?v=73cf2db1" />
	</programme>
	<programme channel="tx" start="20260323190000 +0000" stop="20260324092500 +0000">
		<title>配信準備中</title>
		<desc>配信準備中</desc>
		<icon src="https://statics.tver.jp/images/content/thumbnail/live/xlarge/leu64hme6h.jpg?v=2bc949c1" />
	</programme>
	<programme channel="tx" start="20260324092500 +0000" stop="20260324131000 +0000">
		<title>開運！なんでも鑑定団</title>
		<desc>開運！なんでも鑑定団【春ＳＰ！世界初カラオケ機＆伝説絵師の超大作に衝撃値】</desc>
		<icon src="https://statics.tver.jp/images/content/thumbnail/live/xlarge/le8r6r7b9u.jpg?v=57841bf7" />
	</programme>
	<programme channel="tx" start="20260324131000 +0000" stop="20260324131500 +0000">
		<title>配信準備中</title>
		<desc>配信準備中</desc>
		<icon src="https://statics.tver.jp/images/content/thumbnail/live/xlarge/lenk8qa3aj.jpg?v=2857f86d" />
	</programme>
	<programme channel="tx" start="20260324131500 +0000" stop="20260324141300 +0000">
		<title>ＷＢＳ（ワールドビジネスサテライト）</title>
		<desc>ＷＢＳ【イラン情勢で問合せ殺到「再生重油」▼すかいらーく「しんぱち食堂」買収】</desc>
		<icon src="https://statics.tver.jp/images/content/thumbnail/live/xlarge/les1uvkgq4.jpg?v=541a917a" />
	</programme>
	<programme channel="tx" start="20260324141300 +0000" stop="20260324142100 +0000">
		<title>配信準備中</title>
		<desc>配信準備中</desc>
		<icon src="https://statics.tver.jp/images/content/thumbnail/live/xlarge/le9eus15w4.jpg?v=aaf03fe1" />
	</programme>
	<programme channel="tx" start="20260324142100 +0000" stop="20260324151000 +0000">
		<title>ＬＩＦＥ　ＩＳ　ＭＯＮＥＹ～世の中お金で見てみよう～</title>
		<desc>LIFE　IS　MONEY　～世の中お金で見てみよう～</desc>
		<icon src="https://statics.tver.jp/images/content/thumbnail/live/xlarge/lecx7has9i.jpg?v=0542c2fc" />
	</programme>
	<programme channel="tx" start="20260324151000 +0000" stop="20260324190000 +0000">
		<title>配信準備中</title>
		<desc>配信準備中</desc>
		<icon src="https://statics.tver.jp/images/content/thumbnail/live/xlarge/le19o7wh4a.jpg?v=cc45d636" />
	</programme>
	<programme channel="tx" start="20260324190000 +0000" stop="20260325092500 +0000">
		<title>配信準備中</title>
		<desc>配信準備中</desc>
		<icon src="https://statics.tver.jp/images/content/thumbnail/live/xlarge/lekhpp6ucu.jpg?v=1e4a4098" />
	</programme>
	<programme channel="tx" start="20260325092500 +0000" stop="20260325113000 +0000">
		<title>世界を救う！ワンにゃフル物語～柴と三毛と亀梨くん～</title>
		<desc>激かわ！ワンにゃフル物語★春のモフモフ祭★保護大型犬！６匹大家族＆くるくる毛猫</desc>
		<icon src="https://statics.tver.jp/images/content/thumbnail/live/xlarge/le5puvfqtr.jpg?v=6f2dd231" />
	</programme>
	<programme channel="tx" start="20260325113000 +0000" stop="20260325130900 +0000">
		<title>バカリズムのちょっとバカりハカってみた！</title>
		<desc>バカりハカってみた！大谷翔平超え250キロ打球VS最強老人▼人類未踏絶景へ洞窟探検</desc>
		<icon src="https://statics.tver.jp/images/content/thumbnail/live/xlarge/leqej0l69a.jpg?v=e15c5a2a" />
	</programme>
	<programme channel="tx" start="20260325130900 +0000" stop="20260325131500 +0000">
		<title>配信準備中</title>
		<desc>配信準備中</desc>
		<icon src="https://statics.tver.jp/images/content/thumbnail/live/xlarge/lew7h0bj8f.jpg?v=c13abd52" />
	</programme>
	<programme channel="tx" start="20260325131500 +0000" stop="20260325141300 +0000">
		<title>ＷＢＳ（ワールドビジネスサテライト）</title>
		<desc>ＷＢＳ【再開発進む“品川圏”JR東の狙い▼265兆円運用会社が読み解くイラン情勢】</desc>
		<icon src="https://statics.tver.jp/images/content/thumbnail/live/xlarge/lecunwysk5.jpg?v=2b4782d0" />
	</programme>
	<programme channel="tx" start="20260325141300 +0000" stop="20260325142100 +0000">
		<title>配信準備中</title>
		<desc>配信準備中</desc>
		<icon src="https://statics.tver.jp/images/content/thumbnail/live/xlarge/le1mqitynf.jpg?v=0bfd3759" />
	</programme>
	<programme channel="tx" start="20260325142100 +0000" stop="20260325151000 +0000">
		<title>あちこちオードリー</title>
		<desc>あちこちオードリー【若林5週ぶり復帰！】</desc>
		<icon src="https://statics.tver.jp/images/content/thumbnail/live/xlarge/lek1mxgwia.jpg?v=a2308177" />
	</programme>
	<programme channel="tx" start="20260325151000 +0000" stop="20260325190000 +0000">
		<title>配信準備中</title>
		<desc>配信準備中</desc>
		<icon src="https://statics.tver.jp/images/content/thumbnail/live/xlarge/legawdgrc0.jpg?v=15440a93" />
	</programme>
	<programme channel="tx" start="20260325190000 +0000" stop="20260326092500 +0000">
		<title>配信準備中</title>
		<desc>配信準備中</desc>
		<icon src="https://statics.tver.jp/images/content/thumbnail/live/xlarge/letdlk9d2x.jpg?v=56234060" />
	</programme>
	<programme channel="tx" start="20260326092500 +0000" stop="20260326130500 +0000">
		<title>世界が騒然！本当にあった(秘)衝撃ファイル</title>
		<desc>(秘)衝撃ファイル【動物(秘)珍救出＆手に汗握る(秘)緊迫摘発の瞬間＆23歳女性が謎の死…】</desc>
		<icon src="https://statics.tver.jp/images/content/thumbnail/live/xlarge/lelqdewbmy.jpg?v=b03f38db" />
	</programme>
	<programme channel="tx" start="20260326130500 +0000" stop="20260326131500 +0000">
		<title>配信準備中</title>
		<desc>配信準備中</desc>
		<icon src="https://statics.tver.jp/images/content/thumbnail/live/xlarge/leoipxmak8.jpg?v=c09620af" />
	</programme>
	<programme channel="tx" start="20260326131500 +0000" stop="20260326141300 +0000">
		<title>ＷＢＳ（ワールドビジネスサテライト）</title>
		<desc>ＷＢＳ【米・イラン停戦に向けた交渉は…】</desc>
		<icon src="https://statics.tver.jp/images/content/thumbnail/live/xlarge/le7wbujidz.jpg?v=f1697ccc" />
	</programme>
	<programme channel="tx" start="20260326141300 +0000" stop="20260326142100 +0000">
		<title>配信準備中</title>
		<desc>配信準備中</desc>
		<icon src="https://statics.tver.jp/images/content/thumbnail/live/xlarge/le2h7hftbb.jpg?v=e00f32e9" />
	</programme>
	<programme channel="tx" start="20260326142100 +0000" stop="20260326154000 +0000">
		<title>カンブリア宮殿</title>
		<desc>カンブリア宮殿【村上龍＆小池栄子卒業ＳＰ　未来をつかむ経営とは？】</desc>
		<icon src="https://statics.tver.jp/images/content/thumbnail/live/xlarge/leokrhonbs.jpg?v=d0508f23" />
	</programme>
	<programme channel="tx" start="20260326154000 +0000" stop="20260326190000 +0000">
		<title>配信準備中</title>
		<desc>配信準備中</desc>
		<icon src="https://statics.tver.jp/images/content/thumbnail/live/xlarge/le3m8snwb7.jpg?v=e9527963" />
	</programme>
	<programme channel="tx" start="20260326190000 +0000" stop="20260327092500 +0000">
		<title>配信準備中</title>
		<desc>配信準備中</desc>
		<icon src="https://statics.tver.jp/images/content/thumbnail/live/xlarge/le24m0gr1v.jpg?v=e49a99e7" />
	</programme>
	<programme channel="tx" start="20260327092500 +0000" stop="20260327095500 +0000">
		<title>BEYBLADE X</title>
		<desc>BEYBLADE　X　「その先のX」</desc>
		<icon src="https://statics.tver.jp/images/content/thumbnail/live/xlarge/le3zbeec25.jpg?v=fa91ac0d" />
	</programme>
	<programme channel="tx" start="20260327095500 +0000" stop="20260327105500 +0000">
		<title>配信準備中</title>
		<desc>配信準備中</desc>
		<icon src="https://statics.tver.jp/images/content/thumbnail/live/xlarge/legtf3df60.jpg?v=5bef3762" />
	</programme>
	<programme channel="tx" start="20260327105500 +0000" stop="20260327130900 +0000">
		<title>所でナンじゃこりゃ！？</title>
		<desc>所でナンじゃこりゃ!?鬼滅の刃の世界＆ナスカの地上絵で新発見！令和の禁断ゾーンSP</desc>
		<icon src="https://statics.tver.jp/images/content/thumbnail/live/xlarge/leq4cbu2mn.jpg?v=9b5e9fec" />
	</programme>
	<programme channel="tx" start="20260327130900 +0000" stop="20260327131500 +0000">
		<title>配信準備中</title>
		<desc>配信準備中</desc>
		<icon src="https://statics.tver.jp/images/content/thumbnail/live/xlarge/lehzpltwxm.jpg?v=0a022686" />
	</programme>
	<programme channel="tx" start="20260327131500 +0000" stop="20260327140900 +0000">
		<title>ガイアの夜明け</title>
		<desc>ガイアの夜明け【太陽光はニッポンの切り札か　エネルギー危機の今考える】</desc>
		<icon src="https://statics.tver.jp/images/content/thumbnail/live/xlarge/ley3ahjrkz.jpg?v=ed40f2ac" />
	</programme>
	<programme channel="tx" start="20260327140900 +0000" stop="20260327141500 +0000">
		<title>配信準備中</title>
		<desc>配信準備中</desc>
		<icon src="https://statics.tver.jp/images/content/thumbnail/live/xlarge/lesinz3k1w.jpg?v=50004044" />
	</programme>
	<programme channel="tx" start="20260327141500 +0000" stop="20260327151300 +0000">
		<title>ＷＢＳ（ワールドビジネスサテライト）</title>
		<desc>ＷＢＳ　イラン戦闘“１カ月”で株価＆原油価格はどうなる？</desc>
		<icon src="https://statics.tver.jp/images/content/thumbnail/live/xlarge/leolfiqoua.jpg?v=11251e6d" />
	</programme>
	<programme channel="tx" start="20260327151300 +0000" stop="20260327190000 +0000">
		<title>配信準備中</title>
		<desc>配信準備中</desc>
		<icon src="https://statics.tver.jp/images/content/thumbnail/live/xlarge/lej6l1mmoe.jpg?v=a8b9b8db" />
	</programme>
	<programme channel="tx" start="20260327190000 +0000" stop="20260328093000 +0000">
		<title>配信準備中</title>
		<desc>配信準備中</desc>
		<icon src="https://statics.tver.jp/images/content/thumbnail/live/xlarge/le0sjg50hz.jpg?v=9beff213" />
	</programme>
	<programme channel="tx" start="20260328093000 +0000" stop="20260328115500 +0000">
		<title>出川哲朗の充電させてもらえませんか？</title>
		<desc>出川哲朗の充電させてもらえませんか？初！オズワルド伊藤＆浮所飛貴▼千葉⇒埼玉</desc>
		<icon src="https://statics.tver.jp/images/content/thumbnail/live/xlarge/le3kiybqr2.jpg?v=7f451115" />
	</programme>
	<programme channel="tx" start="20260328115500 +0000" stop="20260328120000 +0000">
		<title>配信準備中</title>
		<desc>配信準備中</desc>
		<icon src="https://statics.tver.jp/images/content/thumbnail/live/xlarge/le6lz2nkvi.jpg?v=ef892082" />
	</programme>
	<programme channel="tx" start="20260328120000 +0000" stop="20260328125400 +0000">
		<title>出没！アド街ック天国</title>
		<desc>出没！アド街ック天国【赤羽】北区で“激安”競争が過熱!?せんべろ＆大衆酒場の聖地</desc>
		<icon src="https://statics.tver.jp/images/content/thumbnail/live/xlarge/lelrcsqlxz.jpg?v=9b83520c" />
	</programme>
	<programme channel="tx" start="20260328125400 +0000" stop="20260328190000 +0000">
		<title>配信準備中</title>
		<desc>配信準備中</desc>
		<icon src="https://statics.tver.jp/images/content/thumbnail/live/xlarge/leftmwjw73.jpg?v=62e0a30d" />
	</programme>
	<programme channel="tx" start="20260328190000 +0000" stop="20260329115000 +0000">
		<title>配信準備中</title>
		<desc>配信準備中</desc>
		<icon src="https://statics.tver.jp/images/content/thumbnail/live/xlarge/leyusl8sli.jpg?v=3dc0092d" />
	</programme>
	<programme channel="tx" start="20260329115000 +0000" stop="20260329125400 +0000">
		<title>家、ついて行ってイイですか？</title>
		<desc>家、ついて行ってイイですか？timelesz熱狂マダムになにわ男子・道枝が物申す！？</desc>
		<icon src="https://statics.tver.jp/images/content/thumbnail/live/xlarge/le5yplji49.jpg?v=3475de6c" />
	</programme>
	<programme channel="tx" start="20260329125400 +0000" stop="20260329130000 +0000">
		<title>配信準備中</title>
		<desc>配信準備中</desc>
		<icon src="https://statics.tver.jp/images/content/thumbnail/live/xlarge/lenl1n9uop.jpg?v=a76c6dae" />
	</programme>
	<programme channel="tx" start="20260329130000 +0000" stop="20260329134800 +0000">
		<title>有吉ぃぃeeeee！～そうだ！今からお前んチでゲームしない？</title>
		<desc>有吉ぃぃeeeee！【最新マリオテニス＆ロブロックス】櫻坂46と話題作2本立てSP</desc>
		<icon src="https://statics.tver.jp/images/content/thumbnail/live/xlarge/lesnnel6jh.jpg?v=c9625154" />
	</programme>
	<programme channel="tx" start="20260329134800 +0000" stop="20260329190000 +0000">
		<title>配信準備中</title>
		<desc>配信準備中</desc>
		<icon src="https://statics.tver.jp/images/content/thumbnail/live/xlarge/lelpq4sp03.jpg?v=90f64821" />
	</programme>
	<programme channel="tx" start="20260329190000 +0000" stop="20260330092500 +0000">
		<title>配信準備中</title>
		<desc>配信準備中</desc>
		<icon src="https://statics.tver.jp/images/content/thumbnail/live/xlarge/le53idbscj.jpg?v=9869e641" />
	</programme>
	<programme channel="tx" start="20260330092500 +0000" stop="20260330110000 +0000">
		<title>YOUは何しに日本へ？</title>
		<desc>ＹＯＵは何しに日本へ？★幕末のおんな侍…弔い旅＆レディー・ガガのメイクさん密着</desc>
		<icon src="https://statics.tver.jp/images/content/thumbnail/live/xlarge/le74tu7g46.jpg?v=c6652e76" />
	</programme>
	<programme channel="tx" start="20260330110000 +0000" stop="20260330115400 +0000">
		<title>ＪＡＰＡＮをスーツケースにつめ込んで！～世界に日本を持ってった～</title>
		<desc>ＪＡＰＡＮをスーツケースにつめ込んで！～世界に日本を持ってった～　ラーメン対決</desc>
		<icon src="https://statics.tver.jp/images/content/thumbnail/live/xlarge/leyqyi3a4d.jpg?v=45744862" />
	</programme>
	<programme channel="tx" start="20260330115400 +0000" stop="20260330125400 +0000">
		<title>世界！ニッポン行きたい人応援団</title>
		<desc>世界！ニッポン行きたい人応援団★吉田兄弟サプライズ登場！津軽三味線の奏法猛特訓</desc>
		<icon src="https://statics.tver.jp/images/content/thumbnail/live/xlarge/lesjkm0unt.jpg?v=fcc17d32" />
	</programme>
	<programme channel="tx" start="20260330125400 +0000" stop="20260330130000 +0000">
		<title>配信準備中</title>
		<desc>配信準備中</desc>
		<icon src="https://statics.tver.jp/images/content/thumbnail/live/xlarge/le8c4ttrim.jpg?v=ca0c82c7" />
	</programme>
	<programme channel="tx" start="20260330130000 +0000" stop="20260330135800 +0000">
		<title>ＷＢＳ（ワールドビジネスサテライト）</title>
		<desc>ＷＢＳ</desc>
		<icon src="https://statics.tver.jp/images/content/thumbnail/live/xlarge/le4u9g6y5h.jpg?v=777fa9af" />
	</programme>
	<programme channel="tx" start="20260330135800 +0000" stop="20260330140600 +0000">
		<title>配信準備中</title>
		<desc>配信準備中</desc>
		<icon src="https://statics.tver.jp/images/content/thumbnail/live/xlarge/lejmfrdr7x.jpg?v=e1922252" />
	</programme>
	<programme channel="tx" start="20260330140600 +0000" stop="20260330145500 +0000">
		<title>産まない女はダメですか？ DINKsのトツキトオカ</title>
		<desc>産まない女はダメですか？－ＤＩＮＫｓのトツキトオカ－</desc>
		<icon src="https://statics.tver.jp/images/content/thumbnail/live/xlarge/le1fza0myu.jpg?v=8c0c572c" />
	</programme>
	<programme channel="tx" start="20260330145500 +0000" stop="20260330190000 +0000">
		<title>配信準備中</title>
		<desc>配信準備中</desc>
		<icon src="https://statics.tver.jp/images/content/thumbnail/live/xlarge/leqty1mj4h.jpg?v=ddfe484a" />
	</programme>
	<programme channel="tx" start="20260330190000 +0000" stop="20260331130000 +0000">
		<title>配信準備中</title>
		<desc>配信準備中</desc>
		<icon src="https://statics.tver.jp/images/content/thumbnail/live/xlarge/ledwmg9xk0.jpg?v=b9605529" />
	</programme>
	<programme channel="tx" start="20260331130000 +0000" stop="20260331135800 +0000">
		<title>ＷＢＳ（ワールドビジネスサテライト）</title>
		<desc>ＷＢＳ</desc>
		<icon src="https://statics.tver.jp/images/content/thumbnail/live/xlarge/lecsvav5jr.jpg?v=1bbfa5c6" />
	</programme>
	<programme channel="tx" start="20260331135800 +0000" stop="20260331140600 +0000">
		<title>配信準備中</title>
		<desc>配信準備中</desc>
		<icon src="https://statics.tver.jp/images/content/thumbnail/live/xlarge/lezahksqta.jpg?v=b9a24725" />
	</programme>
	<programme channel="tx" start="20260331140600 +0000" stop="20260331145500 +0000">
		<title>ＬＩＦＥ　ＩＳ　ＭＯＮＥＹ～世の中お金で見てみよう～</title>
		<desc>LIFE　IS　MONEY　～世の中お金で見てみよう～</desc>
		<icon src="https://statics.tver.jp/images/content/thumbnail/live/xlarge/le3asd1lq4.jpg?v=a1f7ba0b" />
	</programme>
	<programme channel="tx" start="20260331145500 +0000" stop="20260331190000 +0000">
		<title>配信準備中</title>
		<desc>配信準備中</desc>
		<icon src="https://statics.tver.jp/images/content/thumbnail/live/xlarge/leqfqv0mnh.jpg?v=6cfeecc7" />
	</programme>
	<programme channel="tx" start="20260331190000 +0000" stop="20260401092500 +0000">
		<title>配信準備中</title>
		<desc>配信準備中</desc>
		<icon src="https://statics.tver.jp/images/content/thumbnail/live/xlarge/lenef7624g.jpg?v=739f6851" />
	</programme>
	<programme channel="tx" start="20260401092500 +0000" stop="20260401125400 +0000">
		<title>ソレダメ！ ～あなたの常識は非常識！？～</title>
		<desc>ソレダメ！～あなたの常識は非常識！？～</desc>
		<icon src="https://statics.tver.jp/images/content/thumbnail/live/xlarge/le52v7lpi9.jpg?v=92dc6d55" />
	</programme>
	<programme channel="tx" start="20260401125400 +0000" stop="20260401130000 +0000">
		<title>配信準備中</title>
		<desc>配信準備中</desc>
		<icon src="https://statics.tver.jp/images/content/thumbnail/live/xlarge/leat2m0ohe.jpg?v=79990dec" />
	</programme>
	<programme channel="tx" start="20260401130000 +0000" stop="20260401135800 +0000">
		<title>ＷＢＳ（ワールドビジネスサテライト）</title>
		<desc>ＷＢＳ</desc>
		<icon src="https://statics.tver.jp/images/content/thumbnail/live/xlarge/leuylt3cga.jpg?v=885aa564" />
	</programme>
	<programme channel="tx" start="20260401135800 +0000" stop="20260401140600 +0000">
		<title>配信準備中</title>
		<desc>配信準備中</desc>
		<icon src="https://statics.tver.jp/images/content/thumbnail/live/xlarge/led75ptumc.jpg?v=069b1f95" />
	</programme>
	<programme channel="tx" start="20260401140600 +0000" stop="20260401145500 +0000">
		<title>元祖！大食い王決定戦</title>
		<desc>最強大食い王決定戦２０２６【ギャル曽根超え!?関東・甲信越予選全部見せますＳＰ】</desc>
		<icon src="https://statics.tver.jp/images/content/thumbnail/live/xlarge/lew82jrj3p.jpg?v=4b505129" />
	</programme>
	<programme channel="tx" start="20260401145500 +0000" stop="20260401190000 +0000">
		<title>配信準備中</title>
		<desc>配信準備中</desc>
		<icon src="https://statics.tver.jp/images/content/thumbnail/live/xlarge/le183384zf.jpg?v=449a52ad" />
	</programme>
	<programme channel="tx" start="20260401190000 +0000" stop="20260402092500 +0000">
		<title>配信準備中</title>
		<desc>配信準備中</desc>
		<icon src="https://statics.tver.jp/images/content/thumbnail/live/xlarge/le1vvtwqr9.jpg?v=e25b8dee" />
	</programme>
	<programme channel="tx" start="20260402092500 +0000" stop="20260402115800 +0000">
		<title>タクうま～タクシー運転手さん一番うまい店に連れてって！～</title>
		<desc>タクうま～タクシー会社対抗グルメバトル～八王子VS相模原＆宇都宮の新グルメ開拓SP</desc>
		<icon src="https://statics.tver.jp/images/content/thumbnail/live/xlarge/le04uv80pu.jpg?v=58fafcbb" />
	</programme>
	<programme channel="tx" start="20260402115800 +0000" stop="20260402125400 +0000">
		<title>ナゼそこ？＋</title>
		<desc>ナゼそこ？「長野・新潟の県境…南極で人類初の大偉業！実はスゴい秘境人」SP</desc>
		<icon src="https://statics.tver.jp/images/content/thumbnail/live/xlarge/ler5ojaoot.jpg?v=99b16890" />
	</programme>
	<programme channel="tx" start="20260402125400 +0000" stop="20260402130000 +0000">
		<title>配信準備中</title>
		<desc>配信準備中</desc>
		<icon src="https://statics.tver.jp/images/content/thumbnail/live/xlarge/lex1q0wo8d.jpg?v=9c05256e" />
	</programme>
	<programme channel="tx" start="20260402130000 +0000" stop="20260402135800 +0000">
		<title>ＷＢＳ（ワールドビジネスサテライト）</title>
		<desc>ＷＢＳ</desc>
		<icon src="https://statics.tver.jp/images/content/thumbnail/live/xlarge/ley1v0s29a.jpg?v=084182f0" />
	</programme>
	<programme channel="tx" start="20260402135800 +0000" stop="20260402140600 +0000">
		<title>配信準備中</title>
		<desc>配信準備中</desc>
		<icon src="https://statics.tver.jp/images/content/thumbnail/live/xlarge/lennax0cod.jpg?v=2b45a30d" />
	</programme>
	<programme channel="tx" start="20260402140600 +0000" stop="20260402152500 +0000">
		<title>カンブリア宮殿</title>
		<desc>カンブリア宮殿リニューアルSP【“最強の商人”が語る　伊藤忠商事　稼ぐ秘訣】</desc>
		<icon src="https://statics.tver.jp/images/content/thumbnail/live/xlarge/le88rzo9m0.jpg?v=6accf003" />
	</programme>
	<programme channel="tx" start="20260402152500 +0000" stop="20260402190000 +0000">
		<title>配信準備中</title>
		<desc>配信準備中</desc>
		<icon src="https://statics.tver.jp/images/content/thumbnail/live/xlarge/lekqmlbexj.jpg?v=72d26bf8" />
	</programme>
	<programme channel="tx" start="20260402190000 +0000" stop="20260403105500 +0000">
		<title>配信準備中</title>
		<desc>配信準備中</desc>
		<icon src="https://statics.tver.jp/images/content/thumbnail/live/xlarge/lep6h6ipnf.jpg?v=15e2f317" />
	</programme>
	<programme channel="cx" start="20260320110000 +0000" stop="20260320125200 +0000">
		<title>地上波放送番組のお知らせ</title>
		<desc>映画「えんとつ町のプペル」は地上波放送でお楽しみください！</desc>
		<icon src="https://statics.tver.jp/images/content/thumbnail/live/xlarge/leq9jmcnwp.jpg?v=ccf19a18" />
	</programme>
	<programme channel="cx" start="20260320125200 +0000" stop="20260320125800 +0000">
		<title>配信番組のお知らせ</title>
		<desc>🐶🐩🐕</desc>
		<icon src="https://statics.tver.jp/images/content/thumbnail/live/xlarge/leuqn8737l.jpg?v=7bcbe184" />
	</programme>
	<programme channel="cx" start="20260320125800 +0000" stop="20260320135200 +0000">
		<title>タイムレスマン</title>
		<desc>▼来月からのゴールデンレギュラーに先駆けてプレオープンSP！</desc>
		<icon src="https://statics.tver.jp/images/content/thumbnail/live/xlarge/leb8j0ldei.jpg?v=4b4728cb" />
	</programme>
	<programme channel="cx" start="20260320135200 +0000" stop="20260320140000 +0000">
		<title>配信番組のお知らせ</title>
		<desc>🐶🐩🐕</desc>
		<icon src="https://statics.tver.jp/images/content/thumbnail/live/xlarge/le763g7qig.jpg?v=7018d964" />
	</programme>
	<programme channel="cx" start="20260320140000 +0000" stop="20260320143000 +0000">
		<title>全力！脱力タイムズ</title>
		<desc>堂本剛＆ますおか岡田▼剛くん、俺のこと覚えてるかな？</desc>
		<icon src="https://statics.tver.jp/images/content/thumbnail/live/xlarge/le2q128tl5.jpg?v=5de3e4ca" />
	</programme>
	<programme channel="cx" start="20260320143000 +0000" stop="20260321093000 +0000">
		<title>No programme</title>
		<desc>No programme</desc>
		<icon src="https://statics.tver.jp/images/icon/cx.jpg" />
	</programme>
	<programme channel="cx" start="20260321093000 +0000" stop="20260321115400 +0000">
		<title>R-1グランプリ 2026</title>
		<desc>ピン芸日本一決定戦！優勝賞金５００万円！</desc>
		<icon src="https://statics.tver.jp/images/content/thumbnail/live/xlarge/lefh0wcqb2.jpg?v=b20ea3d6" />
	</programme>
	<programme channel="cx" start="20260321115400 +0000" stop="20260321120000 +0000">
		<title>配信番組のお知らせ</title>
		<desc>🐶🐩🐕</desc>
		<icon src="https://statics.tver.jp/images/content/thumbnail/live/xlarge/letkrvh8r3.jpg?v=f666c5d6" />
	</programme>
	<programme channel="cx" start="20260321120000 +0000" stop="20260321141000 +0000">
		<title>ENGEIグランドスラム</title>
		<desc>【LIVE】超豪華！賞レース王者＆MCクラス集結</desc>
		<icon src="https://statics.tver.jp/images/content/thumbnail/live/xlarge/le3rwhjim6.jpg?v=d981da00" />
	</programme>
	<programme channel="cx" start="20260321141000 +0000" stop="20260321144000 +0000">
		<title>さんまのお笑い向上委員会</title>
		<desc>▼令和の天才VS昭和の天才ダウ90000さんまに初対面</desc>
		<icon src="https://statics.tver.jp/images/content/thumbnail/live/xlarge/ledbdkfjqp.jpg?v=162ecd98" />
	</programme>
	<programme channel="cx" start="20260321144000 +0000" stop="20260322100000 +0000">
		<title>No programme</title>
		<desc>No programme</desc>
		<icon src="https://statics.tver.jp/images/icon/cx.jpg" />
	</programme>
	<programme channel="cx" start="20260322100000 +0000" stop="20260322115400 +0000">
		<title>千鳥の鬼レンチャン</title>
		<desc>◆初代鬼レンMayJ.鬼ハード制覇へ＆第２回クレーンゲーム</desc>
		<icon src="https://statics.tver.jp/images/content/thumbnail/live/xlarge/leoz9hnwm4.jpg?v=3f3a471b" />
	</programme>
	<programme channel="cx" start="20260322115400 +0000" stop="20260322140900 +0000">
		<title>地上波放送番組のお知らせ</title>
		<desc>「Mr.サンデー」は地上波放送でお楽しみください！</desc>
		<icon src="https://statics.tver.jp/images/content/thumbnail/live/xlarge/leibdsv86r.jpg?v=94820015" />
	</programme>
	<programme channel="cx" start="20260322140900 +0000" stop="20260322141500 +0000">
		<title>配信番組のお知らせ</title>
		<desc>🐶🐩🐕</desc>
		<icon src="https://statics.tver.jp/images/content/thumbnail/live/xlarge/lexrjl6hbl.jpg?v=4a1b1ebb" />
	</programme>
	<programme channel="cx" start="20260322141500 +0000" stop="20260322144500 +0000">
		<title>世界で一番怖い答え</title>
		<desc>★有田哲平が贈る最恐クイズ最新作登場！映像に隠された恐怖とは</desc>
		<icon src="https://statics.tver.jp/images/content/thumbnail/live/xlarge/lebyeaxn1g.jpg?v=f32a4fdb" />
	</programme>
	<programme channel="cx" start="20260322144500 +0000" stop="20260323100000 +0000">
		<title>No programme</title>
		<desc>No programme</desc>
		<icon src="https://statics.tver.jp/images/icon/cx.jpg" />
	</programme>
	<programme channel="cx" start="20260323100000 +0000" stop="20260323120000 +0000">
		<title>ネプリーグ</title>
		<desc>２時間SP★俳優vsアイドルvs芸人！頭いいのは？芸能界三つ巴対決</desc>
		<icon src="https://statics.tver.jp/images/content/thumbnail/live/xlarge/lemsd4lhrq.jpg?v=b7d63834" />
	</programme>
	<programme channel="cx" start="20260323120000 +0000" stop="20260323125400 +0000">
		<title>ヤンドク！</title>
		<desc>第11話 最期に残された希望とは？恩師の病を治すことはできるのか</desc>
		<icon src="https://statics.tver.jp/images/content/thumbnail/live/xlarge/leka9z4umk.jpg?v=a1c3cd22" />
	</programme>
	<programme channel="cx" start="20260323125400 +0000" stop="20260323130000 +0000">
		<title>配信番組のお知らせ</title>
		<desc>🐶🐩🐕</desc>
		<icon src="https://statics.tver.jp/images/content/thumbnail/live/xlarge/le1pq3ji89.jpg?v=dd709390" />
	</programme>
	<programme channel="cx" start="20260323130000 +0000" stop="20260323135400 +0000">
		<title>夫に間違いありません</title>
		<desc>#12 家族のために罪を犯した女は聖母か悪女か</desc>
		<icon src="https://statics.tver.jp/images/content/thumbnail/live/xlarge/leg331loyl.jpg?v=a239caac" />
	</programme>
	<programme channel="cx" start="20260323135400 +0000" stop="20260323140000 +0000">
		<title>配信番組のお知らせ</title>
		<desc>🐶🐩🐕</desc>
		<icon src="https://statics.tver.jp/images/content/thumbnail/live/xlarge/le27hjbz5s.jpg?v=f6430c75" />
	</programme>
	<programme channel="cx" start="20260323140000 +0000" stop="20260323143000 +0000">
		<title>けるとめる</title>
		<desc>トラジャがＪリーガー奥様に料理をふるまう！イケメン夫の㊙エピも</desc>
		<icon src="https://statics.tver.jp/images/content/thumbnail/live/xlarge/leww35i7jz.jpg?v=68d52eca" />
	</programme>
	<programme channel="cx" start="20260323143000 +0000" stop="20260324100000 +0000">
		<title>No programme</title>
		<desc>No programme</desc>
		<icon src="https://statics.tver.jp/images/icon/cx.jpg" />
	</programme>
	<programme channel="cx" start="20260324100000 +0000" stop="20260324120000 +0000">
		<title>配信番組のお知らせ</title>
		<desc>🐶🐩🐕</desc>
		<icon src="https://statics.tver.jp/images/content/thumbnail/live/xlarge/lehrad89zr.jpg?v=06c4a634" />
	</programme>
	<programme channel="cx" start="20260324120000 +0000" stop="20260324125400 +0000">
		<title>東京P.D. 警視庁広報2係</title>
		<desc>第9話 “真犯人”の告白！刑事部VS公安部の攻防</desc>
		<icon src="https://statics.tver.jp/images/content/thumbnail/live/xlarge/lexx3adiec.jpg?v=4ad2812e" />
	</programme>
	<programme channel="cx" start="20260324125400 +0000" stop="20260324130000 +0000">
		<title>配信番組のお知らせ</title>
		<desc>🐶🐩🐕</desc>
		<icon src="https://statics.tver.jp/images/content/thumbnail/live/xlarge/lep7suwb5o.jpg?v=0b74c187" />
	</programme>
	<programme channel="cx" start="20260324130000 +0000" stop="20260324135400 +0000">
		<title>火曜は全力！華大さんと千鳥くん</title>
		<desc>間宮祥太朗と食べまくり！松屋人気メニュー当てたら100万</desc>
		<icon src="https://statics.tver.jp/images/content/thumbnail/live/xlarge/leso1mgnws.jpg?v=b1e7ebf3" />
	</programme>
	<programme channel="cx" start="20260324135400 +0000" stop="20260324140000 +0000">
		<title>配信番組のお知らせ</title>
		<desc>🐶🐩🐕</desc>
		<icon src="https://statics.tver.jp/images/content/thumbnail/live/xlarge/lexvzsp1eg.jpg?v=47a4dd35" />
	</programme>
	<programme channel="cx" start="20260324140000 +0000" stop="20260325100000 +0000">
		<title>No programme</title>
		<desc>No programme</desc>
		<icon src="https://statics.tver.jp/images/icon/cx.jpg" />
	</programme>
	<programme channel="cx" start="20260325100000 +0000" stop="20260325120000 +0000">
		<title>奇跡体験！アンビリバボー</title>
		<desc>凶悪犯を捕まえろ！驚異のニッポン捜査SP！</desc>
		<icon src="https://statics.tver.jp/images/content/thumbnail/live/xlarge/lez7zk4ykt.jpg?v=8e2209bf" />
	</programme>
	<programme channel="cx" start="20260325120000 +0000" stop="20260325125400 +0000">
		<title>ホンマでっか！？TV</title>
		<desc>痩せ体質になる食べ方SP</desc>
		<icon src="https://statics.tver.jp/images/content/thumbnail/live/xlarge/lehlqkf62d.jpg?v=f42361de" />
	</programme>
	<programme channel="cx" start="20260325125400 +0000" stop="20260325130000 +0000">
		<title>配信番組のお知らせ</title>
		<desc>🐶🐩🐕</desc>
		<icon src="https://statics.tver.jp/images/content/thumbnail/live/xlarge/lekp176xsl.jpg?v=24d4f98d" />
	</programme>
	<programme channel="cx" start="20260325130000 +0000" stop="20260325135400 +0000">
		<title>ラムネモンキー</title>
		<desc>第11話 守れなかった恩師との約束…取り戻せ！謎と情熱の毎日</desc>
		<icon src="https://statics.tver.jp/images/content/thumbnail/live/xlarge/le9v9uulkt.jpg?v=3145fdc3" />
	</programme>
	<programme channel="cx" start="20260325135400 +0000" stop="20260325140000 +0000">
		<title>配信番組のお知らせ</title>
		<desc>🐶🐩🐕</desc>
		<icon src="https://statics.tver.jp/images/content/thumbnail/live/xlarge/levu1f853e.jpg?v=bfeedae4" />
	</programme>
	<programme channel="cx" start="20260325140000 +0000" stop="20260325143000 +0000">
		<title>週刊ナイナイミュージック</title>
		<desc>涙の最終回！？HANA増田貴久ビーファano</desc>
		<icon src="https://statics.tver.jp/images/content/thumbnail/live/xlarge/lezfavheq3.jpg?v=20651282" />
	</programme>
	<programme channel="cx" start="20260325143000 +0000" stop="20260326100000 +0000">
		<title>No programme</title>
		<desc>No programme</desc>
		<icon src="https://statics.tver.jp/images/icon/cx.jpg" />
	</programme>
	<programme channel="cx" start="20260326100000 +0000" stop="20260326120000 +0000">
		<title>街グルメをマジ探索！かまいまち</title>
		<desc>羽田空港グルメSP</desc>
		<icon src="https://statics.tver.jp/images/content/thumbnail/live/xlarge/lee1ryx9e6.jpg?v=134efc8b" />
	</programme>
	<programme channel="cx" start="20260326120000 +0000" stop="20260326134800 +0000">
		<title>この世界は1ダフル</title>
		<desc>★沖縄好き１万人に聞いた最強スポット１日で全部回りますツアー</desc>
		<icon src="https://statics.tver.jp/images/content/thumbnail/live/xlarge/leiwfqe048.jpg?v=21db20dc" />
	</programme>
	<programme channel="cx" start="20260326134800 +0000" stop="20260326135400 +0000">
		<title>配信番組のお知らせ</title>
		<desc>🐶🐩🐕</desc>
		<icon src="https://statics.tver.jp/images/content/thumbnail/live/xlarge/lenw16kfrf.jpg?v=5eb8c9ce" />
	</programme>
	<programme channel="cx" start="20260326135400 +0000" stop="20260326140000 +0000">
		<title>配信番組のお知らせ</title>
		<desc>🐶🐩🐕</desc>
		<icon src="https://statics.tver.jp/images/content/thumbnail/live/xlarge/lelfz6de0y.jpg?v=dcdab7c5" />
	</programme>
	<programme channel="cx" start="20260326140000 +0000" stop="20260326143000 +0000">
		<title>トークィーンズ</title>
		<desc>韓国旅SP完結編！ILLITとデコボールペン作り＆ドバイチョコ</desc>
		<icon src="https://statics.tver.jp/images/content/thumbnail/live/xlarge/le5c6gygnu.jpg?v=a3c9c27e" />
	</programme>
	<programme channel="cx" start="20260326143000 +0000" stop="20260327100000 +0000">
		<title>No programme</title>
		<desc>No programme</desc>
		<icon src="https://statics.tver.jp/images/icon/cx.jpg" />
	</programme>
	<programme channel="cx" start="20260327100000 +0000" stop="20260327120000 +0000">
		<title>坂上どうぶつ王国</title>
		<desc>＜配信は20時から＞独占密着！ABC-Z塚田の保護犬が脚を切断…手術と闘病全記録</desc>
		<icon src="https://statics.tver.jp/images/content/thumbnail/live/xlarge/le48u2eklw.jpg?v=0630e3e2" />
	</programme>
	<programme channel="cx" start="20260327120000 +0000" stop="20260327135200 +0000">
		<title>世界フィギュアスケート選手権2026</title>
		<desc>男女ショート・ペアフリー</desc>
		<icon src="https://statics.tver.jp/images/content/thumbnail/live/xlarge/le68up24ik.jpg?v=c6f18e65" />
	</programme>
	<programme channel="cx" start="20260327135200 +0000" stop="20260327140000 +0000">
		<title>配信番組のお知らせ</title>
		<desc>🐶🐩🐕</desc>
		<icon src="https://statics.tver.jp/images/content/thumbnail/live/xlarge/leol3w4ja0.jpg?v=c2cb84f9" />
	</programme>
	<programme channel="cx" start="20260327140000 +0000" stop="20260327143000 +0000">
		<title>全力！脱力タイムズ</title>
		<desc>ウエストランド井口＆HARUA▼どういうトリック！？</desc>
		<icon src="https://statics.tver.jp/images/content/thumbnail/live/xlarge/letbxbv7jt.jpg?v=5ba2b491" />
	</programme>
	<programme channel="cx" start="20260327143000 +0000" stop="20260328100000 +0000">
		<title>No programme</title>
		<desc>No programme</desc>
		<icon src="https://statics.tver.jp/images/icon/cx.jpg" />
	</programme>
	<programme channel="cx" start="20260328100000 +0000" stop="20260328120000 +0000">
		<title>芸能人が本気で考えた！ドッキリGP</title>
		<desc>スノーマン＆タイムレス春の秒祭りSP</desc>
		<icon src="https://statics.tver.jp/images/content/thumbnail/live/xlarge/le8ytih9d2.jpg?v=a0895ae3" />
	</programme>
	<programme channel="cx" start="20260328120000 +0000" stop="20260328141000 +0000">
		<title>芸能界特技王決定戦 TEPPEN</title>
		<desc>ピアノ史上最高レベルの対決！今夜新スター誕生！？SP</desc>
		<icon src="https://statics.tver.jp/images/content/thumbnail/live/xlarge/lelopn5zym.jpg?v=97dada4f" />
	</programme>
	<programme channel="cx" start="20260328141000 +0000" stop="20260328144000 +0000">
		<title>さんまのお笑い向上委員会</title>
		<desc>▼センス系集団ダウ90000VS非センス系芸人軍団！</desc>
		<icon src="https://statics.tver.jp/images/content/thumbnail/live/xlarge/le4vw5r89g.jpg?v=75c1ff67" />
	</programme>
	<programme channel="cx" start="20260328144000 +0000" stop="20260329100000 +0000">
		<title>No programme</title>
		<desc>No programme</desc>
		<icon src="https://statics.tver.jp/images/icon/cx.jpg" />
	</programme>
	<programme channel="cx" start="20260329100000 +0000" stop="20260329124700 +0000">
		<title>世界フィギュアスケート選手権2026</title>
		<desc>男女フリー 坂本花織最高のフィナーレへ</desc>
		<icon src="https://statics.tver.jp/images/content/thumbnail/live/xlarge/lesf2ib1ly.jpg?v=35f1f153" />
	</programme>
	<programme channel="cx" start="20260329124700 +0000" stop="20260329125000 +0000">
		<title>配信番組のお知らせ</title>
		<desc>🐶🐩🐕</desc>
		<icon src="https://statics.tver.jp/images/content/thumbnail/live/xlarge/le1bzw1esu.jpg?v=690e5492" />
	</programme>
	<programme channel="cx" start="20260329125000 +0000" stop="20260329140900 +0000">
		<title>地上波放送番組のお知らせ</title>
		<desc>「Mr.サンデー」は地上波放送でお楽しみください！</desc>
		<icon src="https://statics.tver.jp/images/content/thumbnail/live/xlarge/lepa8mvdco.jpg?v=999e5bb1" />
	</programme>
	<programme channel="cx" start="20260329140900 +0000" stop="20260330100000 +0000">
		<title>No programme</title>
		<desc>No programme</desc>
		<icon src="https://statics.tver.jp/images/icon/cx.jpg" />
	</programme>
	<programme channel="cx" start="20260330100000 +0000" stop="20260330125400 +0000">
		<title>地上波放送番組のお知らせ</title>
		<desc>「FNS新ドラマ大集合！国民が熱狂した伝説ドラマ名場面73連発国民的ヒットの祭典」は地上波放送でお楽しみください！</desc>
		<icon src="https://statics.tver.jp/images/content/thumbnail/live/xlarge/lezpboc3nf.jpg?v=fbdf5e54" />
	</programme>
	<programme channel="cx" start="20260330125400 +0000" stop="20260330130000 +0000">
		<title>配信番組のお知らせ</title>
		<desc>🐶🐩🐕</desc>
		<icon src="https://statics.tver.jp/images/content/thumbnail/live/xlarge/leipk079e0.jpg?v=cc29d688" />
	</programme>
	<programme channel="cx" start="20260330130000 +0000" stop="20260330135400 +0000">
		<title>カズレーザー＆石井亮次も知らない神研究！シャーベル賞</title>
		<desc>空気からDNA！？腸活㊙菌</desc>
		<icon src="https://statics.tver.jp/images/content/thumbnail/live/xlarge/lelpihmrus.jpg?v=43f33544" />
	</programme>
	<programme channel="cx" start="20260330135400 +0000" stop="20260330140000 +0000">
		<title>配信番組のお知らせ</title>
		<desc>🐶🐩🐕</desc>
		<icon src="https://statics.tver.jp/images/content/thumbnail/live/xlarge/le7sglm5ii.jpg?v=f09fe380" />
	</programme>
	<programme channel="cx" start="20260330140000 +0000" stop="20260330143000 +0000">
		<title>けるとめる</title>
		<desc>松田元太も絶賛！七五三掛が明日作れる料理をＪリーガー妻にふるまう</desc>
		<icon src="https://statics.tver.jp/images/content/thumbnail/live/xlarge/legs300gq2.jpg?v=de95da65" />
	</programme>
	<programme channel="cx" start="20260330143000 +0000" stop="20260331100000 +0000">
		<title>No programme</title>
		<desc>No programme</desc>
		<icon src="https://statics.tver.jp/images/icon/cx.jpg" />
	</programme>
	<programme channel="cx" start="20260331100000 +0000" stop="20260331120000 +0000">
		<title>配信番組のお知らせ</title>
		<desc>🐶🐩🐕</desc>
		<icon src="https://statics.tver.jp/images/content/thumbnail/live/xlarge/le7mxbar0c.jpg?v=76c04d5c" />
	</programme>
	<programme channel="cx" start="20260331120000 +0000" stop="20260331125400 +0000">
		<title>東京P.D. 警視庁広報2係</title>
		<desc>第10話 刑事部VS公安部！再捜査なるのか迫る時効</desc>
		<icon src="https://statics.tver.jp/images/content/thumbnail/live/xlarge/lelzs9xmmt.jpg?v=a9345969" />
	</programme>
	<programme channel="cx" start="20260331125400 +0000" stop="20260331130000 +0000">
		<title>配信番組のお知らせ</title>
		<desc>🐶🐩🐕</desc>
		<icon src="https://statics.tver.jp/images/content/thumbnail/live/xlarge/len6xg20j3.jpg?v=3c46a20f" />
	</programme>
	<programme channel="cx" start="20260331130000 +0000" stop="20260331142400 +0000">
		<title>不思議体験ファイル 信じてください！！</title>
		<desc>2022年Ｗ杯ドイツ戦に映った神の手</desc>
		<icon src="https://statics.tver.jp/images/content/thumbnail/live/xlarge/le7lt4qs7e.jpg?v=37e0c0d8" />
	</programme>
	<programme channel="cx" start="20260401100000 +0000" stop="20260401120000 +0000">
		<title>世界の何だコレ！？ミステリー</title>
		<desc>２時間SP</desc>
		<icon src="https://statics.tver.jp/images/content/thumbnail/live/xlarge/le15kr1z2y.jpg?v=265969bb" />
	</programme>
	<programme channel="cx" start="20260401120000 +0000" stop="20260401134800 +0000">
		<title>ホンマでっか！？TV</title>
		<desc>若返り２大検証SP郷ひろみ若さの秘密とは？</desc>
		<icon src="https://statics.tver.jp/images/content/thumbnail/live/xlarge/ledngsspi6.jpg?v=a618e6d4" />
	</programme>
	<programme channel="cx" start="20260401134800 +0000" stop="20260401135400 +0000">
		<title>配信番組のお知らせ</title>
		<desc>🐶🐩🐕</desc>
		<icon src="https://statics.tver.jp/images/content/thumbnail/live/xlarge/lepjqhk6qs.jpg?v=6cab85de" />
	</programme>
	<programme channel="cx" start="20260401135400 +0000" stop="20260401140000 +0000">
		<title>配信番組のお知らせ</title>
		<desc>🐶🐩🐕</desc>
		<icon src="https://statics.tver.jp/images/content/thumbnail/live/xlarge/lekwzbf318.jpg?v=6b319ac4" />
	</programme>
	<programme channel="cx" start="20260402100000 +0000" stop="20260402120000 +0000">
		<title>地上波放送番組のお知らせ</title>
		<desc>「超ド級！世界のありえない最強映像60連発衝撃の瞬間＆可愛すぎキッズ＆感動家族愛」は地上波放送でお楽しみください！</desc>
		<icon src="https://statics.tver.jp/images/content/thumbnail/live/xlarge/leyofltoow.jpg?v=d9c44cee" />
	</programme>
	<programme channel="cx" start="20260402120000 +0000" stop="20260402134800 +0000">
		<title>ナゾトレMAXXX</title>
		<desc>３大春の新生活SP★無印良品★文房具★最新パン◆新常識</desc>
		<icon src="https://statics.tver.jp/images/content/thumbnail/live/xlarge/leornata9g.jpg?v=f4381b06" />
	</programme>
	<programme channel="cx" start="20260402134800 +0000" stop="20260402135400 +0000">
		<title>配信番組のお知らせ</title>
		<desc>🐶🐩🐕</desc>
		<icon src="https://statics.tver.jp/images/content/thumbnail/live/xlarge/leb2ht5g02.jpg?v=401a2cc4" />
	</programme>
	<programme channel="cx" start="20260402135400 +0000" stop="20260402140000 +0000">
		<title>配信番組のお知らせ</title>
		<desc>🐶🐩🐕</desc>
		<icon src="https://statics.tver.jp/images/content/thumbnail/live/xlarge/lekuv1ms1x.jpg?v=abcf74ca" />
	</programme>
	<programme channel="cx" start="20260402140000 +0000" stop="20260402143000 +0000">
		<title>世界で一番怖い答え</title>
		<desc>★有田哲平が贈る最恐クイズ！映像に隠された恐怖とは？</desc>
		<icon src="https://statics.tver.jp/images/content/thumbnail/live/xlarge/ley3bufnxh.jpg?v=dc756f84" />
	</programme>
	<programme channel="cx" start="20260403100000 +0000" stop="20260403120000 +0000">
		<title>ウワサのお客さま</title>
		<desc>＜配信は20時から＞▼大関・安青錦が爆食！安治川部屋宮崎牛１頭100kgパーティー</desc>
		<icon src="https://statics.tver.jp/images/content/thumbnail/live/xlarge/le7emc80bu.jpg?v=385b324b" />
	</programme>
</tv>